{
"meta":{"test_sets":[],"test_metrics":[],"learn_metrics":[{"best_value":"Min","name":"RMSE"}],"launch_mode":"Train","parameters":"","iteration_count":1000,"learn_sets":["learn"],"name":"experiment"},
"iterations":[
{"learn":[0.6695772786],"iteration":0,"passed_time":0.06293009056,"remaining_time":62.86716047},
{"learn":[0.6501466398],"iteration":1,"passed_time":0.06706010859,"remaining_time":33.46299419},
{"learn":[0.6318555202],"iteration":2,"passed_time":0.06993178131,"remaining_time":23.24066199},
{"learn":[0.6151770651],"iteration":3,"passed_time":0.0730246916,"remaining_time":18.18314821},
{"learn":[0.6011679595],"iteration":4,"passed_time":0.07559279736,"remaining_time":15.04296667},
{"learn":[0.58788371],"iteration":5,"passed_time":0.07855863078,"remaining_time":13.0145465},
{"learn":[0.5763436852],"iteration":6,"passed_time":0.08208030799,"remaining_time":11.64367798},
{"learn":[0.5651884778],"iteration":7,"passed_time":0.08598108891,"remaining_time":10.66165502},
{"learn":[0.5551773589],"iteration":8,"passed_time":0.08993053309,"remaining_time":9.902350921},
{"learn":[0.546381653],"iteration":9,"passed_time":0.09603506523,"remaining_time":9.507471458},
{"learn":[0.53869537],"iteration":10,"passed_time":0.09872928891,"remaining_time":8.876660612},
{"learn":[0.5320353833],"iteration":11,"passed_time":0.1017857422,"remaining_time":8.380359445},
{"learn":[0.525787795],"iteration":12,"passed_time":0.1062334924,"remaining_time":8.065573618},
{"learn":[0.519963198],"iteration":13,"passed_time":0.1102545166,"remaining_time":7.765068098},
{"learn":[0.5149782881],"iteration":14,"passed_time":0.1138292328,"remaining_time":7.474786289},
{"learn":[0.510447052],"iteration":15,"passed_time":0.1179953738,"remaining_time":7.256715491},
{"learn":[0.5058938148],"iteration":16,"passed_time":0.1217837021,"remaining_time":7.041963478},
{"learn":[0.5019863294],"iteration":17,"passed_time":0.1262908239,"remaining_time":6.889866061},
{"learn":[0.4986200582],"iteration":18,"passed_time":0.1298446663,"remaining_time":6.70408514},
{"learn":[0.4951620453],"iteration":19,"passed_time":0.1337655711,"remaining_time":6.554512984},
{"learn":[0.4922283833],"iteration":20,"passed_time":0.1372282516,"remaining_time":6.397450397},
{"learn":[0.4894002228],"iteration":21,"passed_time":0.1408594637,"remaining_time":6.261843431},
{"learn":[0.4870618344],"iteration":22,"passed_time":0.1447319132,"remaining_time":6.147959965},
{"learn":[0.4850869027],"iteration":23,"passed_time":0.147796991,"remaining_time":6.010410969},
{"learn":[0.4829845792],"iteration":24,"passed_time":0.1515554049,"remaining_time":5.910660793},
{"learn":[0.4809987125],"iteration":25,"passed_time":0.1551807013,"remaining_time":5.813307812},
{"learn":[0.4793489044],"iteration":26,"passed_time":0.1587501679,"remaining_time":5.720885679},
{"learn":[0.4778018282],"iteration":27,"passed_time":0.1627992324,"remaining_time":5.651459069},
{"learn":[0.4765520304],"iteration":28,"passed_time":0.167134031,"remaining_time":5.596108417},
{"learn":[0.4751825138],"iteration":29,"passed_time":0.1708494893,"remaining_time":5.524133488},
{"learn":[0.4736301053],"iteration":30,"passed_time":0.1743024624,"remaining_time":5.448357614},
{"learn":[0.4721507251],"iteration":31,"passed_time":0.1780599183,"remaining_time":5.38631253},
{"learn":[0.4711618696],"iteration":32,"passed_time":0.1817823343,"remaining_time":5.32677325},
{"learn":[0.4696902178],"iteration":33,"passed_time":0.1855952041,"remaining_time":5.27308727},
{"learn":[0.4682219328],"iteration":34,"passed_time":0.1892551656,"remaining_time":5.218035279},
{"learn":[0.4672908375],"iteration":35,"passed_time":0.1926612243,"remaining_time":5.15903945},
{"learn":[0.4663000851],"iteration":36,"passed_time":0.1961087806,"remaining_time":5.104128534},
{"learn":[0.4653523388],"iteration":37,"passed_time":0.2000740159,"remaining_time":5.065031666},
{"learn":[0.4643511125],"iteration":38,"passed_time":0.2036668971,"remaining_time":5.018561234},
{"learn":[0.4634741903],"iteration":39,"passed_time":0.2080635252,"remaining_time":4.993524605},
{"learn":[0.4626024748],"iteration":40,"passed_time":0.2115910351,"remaining_time":4.949165918},
{"learn":[0.4619617731],"iteration":41,"passed_time":0.2153422824,"remaining_time":4.911854917},
{"learn":[0.4611745764],"iteration":42,"passed_time":0.2191838576,"remaining_time":4.878115157},
{"learn":[0.4601345156],"iteration":43,"passed_time":0.2225847496,"remaining_time":4.83615956},
{"learn":[0.459616385],"iteration":44,"passed_time":0.2260573886,"remaining_time":4.797440135},
{"learn":[0.4591071675],"iteration":45,"passed_time":0.2297549309,"remaining_time":4.76491748},
{"learn":[0.4581780477],"iteration":46,"passed_time":0.2333054395,"remaining_time":4.730640082},
{"learn":[0.4578107353],"iteration":47,"passed_time":0.2367299972,"remaining_time":4.695144943},
{"learn":[0.4570144953],"iteration":48,"passed_time":0.2405831557,"remaining_time":4.669277165},
{"learn":[0.4565011512],"iteration":49,"passed_time":0.2440989173,"remaining_time":4.637879428},
{"learn":[0.4556192621],"iteration":50,"passed_time":0.2478907043,"remaining_time":4.612711341},
{"learn":[0.4549791499],"iteration":51,"passed_time":0.2511913939,"remaining_time":4.579412336},
{"learn":[0.4542110869],"iteration":52,"passed_time":0.2548032331,"remaining_time":4.552804938},
{"learn":[0.4537260349],"iteration":53,"passed_time":0.2586608914,"remaining_time":4.531355616},
{"learn":[0.4532941749],"iteration":54,"passed_time":0.2620195778,"remaining_time":4.501972745},
{"learn":[0.4528169592],"iteration":55,"passed_time":0.2656817471,"remaining_time":4.478635165},
{"learn":[0.4523611304],"iteration":56,"passed_time":0.2690358507,"remaining_time":4.450891355},
{"learn":[0.4518728521],"iteration":57,"passed_time":0.2724744076,"remaining_time":4.425360206},
{"learn":[0.4513585304],"iteration":58,"passed_time":0.2758210116,"remaining_time":4.399111389},
{"learn":[0.4510321155],"iteration":59,"passed_time":0.2790866622,"remaining_time":4.372357708},
{"learn":[0.4502366704],"iteration":60,"passed_time":0.2824747639,"remaining_time":4.348259071},
{"learn":[0.4499139059],"iteration":61,"passed_time":0.28672865,"remaining_time":4.337926995},
{"learn":[0.4494835541],"iteration":62,"passed_time":0.2911996909,"remaining_time":4.331017625},
{"learn":[0.4492860212],"iteration":63,"passed_time":0.2949216068,"remaining_time":4.3132285},
{"learn":[0.4487879707],"iteration":64,"passed_time":0.2983342062,"remaining_time":4.291422812},
{"learn":[0.4484287947],"iteration":65,"passed_time":0.3021984061,"remaining_time":4.276565323},
{"learn":[0.4480445174],"iteration":66,"passed_time":0.3063063424,"remaining_time":4.265430112},
{"learn":[0.4477597815],"iteration":67,"passed_time":0.3100910469,"remaining_time":4.250071407},
{"learn":[0.4472135091],"iteration":68,"passed_time":0.3138571273,"remaining_time":4.234796892},
{"learn":[0.4469541001],"iteration":69,"passed_time":0.3173653893,"remaining_time":4.216425886},
{"learn":[0.4466245927],"iteration":70,"passed_time":0.3211645509,"remaining_time":4.202279828},
{"learn":[0.4464233712],"iteration":71,"passed_time":0.3245351116,"remaining_time":4.182896994},
{"learn":[0.445957774],"iteration":72,"passed_time":0.3279904175,"remaining_time":4.165029001},
{"learn":[0.4456884634],"iteration":73,"passed_time":0.3315692165,"remaining_time":4.149095872},
{"learn":[0.4455866648],"iteration":74,"passed_time":0.3349016544,"remaining_time":4.130453737},
{"learn":[0.4451619731],"iteration":75,"passed_time":0.338718023,"remaining_time":4.11809807},
{"learn":[0.4447243793],"iteration":76,"passed_time":0.3425518077,"remaining_time":4.106172968},
{"learn":[0.4445071406],"iteration":77,"passed_time":0.3461384813,"remaining_time":4.091534355},
{"learn":[0.4441558274],"iteration":78,"passed_time":0.3500033892,"remaining_time":4.080419259},
{"learn":[0.4439328446],"iteration":79,"passed_time":0.3533605336,"remaining_time":4.063646137},
{"learn":[0.4436655401],"iteration":80,"passed_time":0.356986788,"remaining_time":4.050257508},
{"learn":[0.4432586277],"iteration":81,"passed_time":0.3607863666,"remaining_time":4.039047372},
{"learn":[0.4429608104],"iteration":82,"passed_time":0.3644255372,"remaining_time":4.026243585},
{"learn":[0.4426498515],"iteration":83,"passed_time":0.3679144242,"remaining_time":4.012019198},
{"learn":[0.4422370382],"iteration":84,"passed_time":0.3717597083,"remaining_time":4.001883918},
{"learn":[0.4420892907],"iteration":85,"passed_time":0.3750988537,"remaining_time":3.986515724},
{"learn":[0.4419208412],"iteration":86,"passed_time":0.3785399105,"remaining_time":3.972493543},
{"learn":[0.4417423501],"iteration":87,"passed_time":0.3819751345,"remaining_time":3.958651394},
{"learn":[0.4414837216],"iteration":88,"passed_time":0.3855378514,"remaining_time":3.94634812},
{"learn":[0.4411626827],"iteration":89,"passed_time":0.389176855,"remaining_time":3.935010423},
{"learn":[0.4408892382],"iteration":90,"passed_time":0.3933067481,"remaining_time":3.928745429},
{"learn":[0.4405386323],"iteration":91,"passed_time":0.3978256613,"remaining_time":3.926366309},
{"learn":[0.4401782972],"iteration":92,"passed_time":0.4024691915,"remaining_time":3.925156523},
{"learn":[0.4399306191],"iteration":93,"passed_time":0.4059415384,"remaining_time":3.912585466},
{"learn":[0.4397045576],"iteration":94,"passed_time":0.4101242205,"remaining_time":3.906972838},
{"learn":[0.4394986934],"iteration":95,"passed_time":0.4136348984,"remaining_time":3.89506196},
{"learn":[0.4393938534],"iteration":96,"passed_time":0.4168829239,"remaining_time":3.880879178},
{"learn":[0.4390190435],"iteration":97,"passed_time":0.4204828877,"remaining_time":3.870158824},
{"learn":[0.4386489491],"iteration":98,"passed_time":0.4240068978,"remaining_time":3.85889106},
{"learn":[0.4383688401],"iteration":99,"passed_time":0.4278558486,"remaining_time":3.850702638},
{"learn":[0.4380581274],"iteration":100,"passed_time":0.4317997111,"remaining_time":3.843444954},
{"learn":[0.437680267],"iteration":101,"passed_time":0.435202395,"remaining_time":3.831487752},
{"learn":[0.4376320644],"iteration":102,"passed_time":0.4386112876,"remaining_time":3.819750728},
{"learn":[0.4374265952],"iteration":103,"passed_time":0.442147047,"remaining_time":3.809266866},
{"learn":[0.4373291574],"iteration":104,"passed_time":0.4454613198,"remaining_time":3.797027441},
{"learn":[0.4370777131],"iteration":105,"passed_time":0.4494585113,"remaining_time":3.790716124},
{"learn":[0.436816829],"iteration":106,"passed_time":0.4534142472,"remaining_time":3.784102081},
{"learn":[0.436535652],"iteration":107,"passed_time":0.457352276,"remaining_time":3.77739102},
{"learn":[0.4364596967],"iteration":108,"passed_time":0.4609351158,"remaining_time":3.767827414},
{"learn":[0.4361676424],"iteration":109,"passed_time":0.4648213975,"remaining_time":3.760827671},
{"learn":[0.4359565982],"iteration":110,"passed_time":0.4684421521,"remaining_time":3.751757417},
{"learn":[0.4357700558],"iteration":111,"passed_time":0.4723328916,"remaining_time":3.744925069},
{"learn":[0.4355284048],"iteration":112,"passed_time":0.4761027629,"remaining_time":3.737196024},
{"learn":[0.4352974088],"iteration":113,"passed_time":0.4798586349,"remaining_time":3.729427636},
{"learn":[0.4350427919],"iteration":114,"passed_time":0.4839335311,"remaining_time":3.72418413},
{"learn":[0.4347786876],"iteration":115,"passed_time":0.4889940798,"remaining_time":3.726472126},
{"learn":[0.4345178527],"iteration":116,"passed_time":0.4934011243,"remaining_time":3.723702502},
{"learn":[0.4343346106],"iteration":117,"passed_time":0.4981678986,"remaining_time":3.723593954},
{"learn":[0.4342508675],"iteration":118,"passed_time":0.5023161656,"remaining_time":3.718828083},
{"learn":[0.4341763134],"iteration":119,"passed_time":0.5061769908,"remaining_time":3.711964599},
{"learn":[0.4340006247],"iteration":120,"passed_time":0.5106089088,"remaining_time":3.709299429},
{"learn":[0.4339548606],"iteration":121,"passed_time":0.514647307,"remaining_time":3.703773242},
{"learn":[0.4336296104],"iteration":122,"passed_time":0.5184620928,"remaining_time":3.696676873},
{"learn":[0.4335696939],"iteration":123,"passed_time":0.5220656824,"remaining_time":3.688141434},
{"learn":[0.4333711615],"iteration":124,"passed_time":0.5258678438,"remaining_time":3.681074907},
{"learn":[0.4332229215],"iteration":125,"passed_time":0.529728668,"remaining_time":3.67446711},
{"learn":[0.4330372005],"iteration":126,"passed_time":0.5323374805,"remaining_time":3.659296224},
{"learn":[0.4328328287],"iteration":127,"passed_time":0.5352897317,"remaining_time":3.646661297},
{"learn":[0.4326778166],"iteration":128,"passed_time":0.5381990683,"remaining_time":3.633886732},
{"learn":[0.432451189],"iteration":129,"passed_time":0.5417747014,"remaining_time":3.625723002},
{"learn":[0.4323789131],"iteration":130,"passed_time":0.5452308823,"remaining_time":3.616836922},
{"learn":[0.4323309422],"iteration":131,"passed_time":0.5489445077,"remaining_time":3.609726005},
{"learn":[0.4322012586],"iteration":132,"passed_time":0.5526300917,"remaining_time":3.60248338},
{"learn":[0.4321254334],"iteration":133,"passed_time":0.5559695292,"remaining_time":3.593056808},
{"learn":[0.4319941623],"iteration":134,"passed_time":0.5594294189,"remaining_time":3.584492202},
{"learn":[0.4319392497],"iteration":135,"passed_time":0.5630690894,"remaining_time":3.577144804},
{"learn":[0.4315378241],"iteration":136,"passed_time":0.5668324611,"remaining_time":3.570630758},
{"learn":[0.4313896549],"iteration":137,"passed_time":0.5703748871,"remaining_time":3.562776469},
{"learn":[0.4312808708],"iteration":138,"passed_time":0.5742107127,"remaining_time":3.556801609},
{"learn":[0.4310235949],"iteration":139,"passed_time":0.5780764956,"remaining_time":3.55104133},
{"learn":[0.4308866359],"iteration":140,"passed_time":0.5825405788,"remaining_time":3.548952888},
{"learn":[0.4307308],"iteration":141,"passed_time":0.5866482651,"remaining_time":3.544677546},
{"learn":[0.4304368952],"iteration":142,"passed_time":0.5908456544,"remaining_time":3.540942138},
{"learn":[0.430165251],"iteration":143,"passed_time":0.5949585074,"remaining_time":3.536697794},
{"learn":[0.430126591],"iteration":144,"passed_time":0.5984298124,"remaining_time":3.528672342},
{"learn":[0.4301135747],"iteration":145,"passed_time":0.6017891657,"remaining_time":3.520054435},
{"learn":[0.4300560327],"iteration":146,"passed_time":0.6050720644,"remaining_time":3.511064428},
{"learn":[0.4297770171],"iteration":147,"passed_time":0.6081135605,"remaining_time":3.500761848},
{"learn":[0.4296037283],"iteration":148,"passed_time":0.6110221892,"remaining_time":3.489797872},
{"learn":[0.429559356],"iteration":149,"passed_time":0.6146131535,"remaining_time":3.48280787},
{"learn":[0.4295326797],"iteration":150,"passed_time":0.6177589348,"remaining_time":3.473359839},
{"learn":[0.4293998629],"iteration":151,"passed_time":0.6211931169,"remaining_time":3.465603705},
{"learn":[0.429261994],"iteration":152,"passed_time":0.6251287299,"remaining_time":3.460679962},
{"learn":[0.428998506],"iteration":153,"passed_time":0.6291373797,"remaining_time":3.456170281},
{"learn":[0.4289456362],"iteration":154,"passed_time":0.6328615866,"remaining_time":3.450116391},
{"learn":[0.4288342375],"iteration":155,"passed_time":0.6363803469,"remaining_time":3.442980851},
{"learn":[0.4285826332],"iteration":156,"passed_time":0.6401874251,"remaining_time":3.437439486},
{"learn":[0.4284600013],"iteration":157,"passed_time":0.6435788186,"remaining_time":3.429704844},
{"learn":[0.4283310157],"iteration":158,"passed_time":0.6469498793,"remaining_time":3.421917286},
{"learn":[0.4283201416],"iteration":159,"passed_time":0.6501169104,"remaining_time":3.41311378},
{"learn":[0.4281533909],"iteration":160,"passed_time":0.6534083926,"remaining_time":3.405028828},
{"learn":[0.4279850069],"iteration":161,"passed_time":0.6569728174,"remaining_time":3.398414944},
{"learn":[0.4278881202],"iteration":162,"passed_time":0.6603209623,"remaining_time":3.390727886},
{"learn":[0.4276201393],"iteration":163,"passed_time":0.663976757,"remaining_time":3.384662005},
{"learn":[0.4274856687],"iteration":164,"passed_time":0.6677072565,"remaining_time":3.379003389},
{"learn":[0.4274037299],"iteration":165,"passed_time":0.6715356665,"remaining_time":3.373859915},
{"learn":[0.4271673786],"iteration":166,"passed_time":0.6752253342,"remaining_time":3.36804014},
{"learn":[0.4269860722],"iteration":167,"passed_time":0.6792126523,"remaining_time":3.363719802},
{"learn":[0.426715549],"iteration":168,"passed_time":0.6832436339,"remaining_time":3.359618105},
{"learn":[0.4265288278],"iteration":169,"passed_time":0.6871713723,"remaining_time":3.355013171},
{"learn":[0.4265137938],"iteration":170,"passed_time":0.6905709733,"remaining_time":3.347855771},
{"learn":[0.4262454303],"iteration":171,"passed_time":0.6943977994,"remaining_time":3.342798709},
{"learn":[0.4260293663],"iteration":172,"passed_time":0.6979914316,"remaining_time":3.336641121},
{"learn":[0.4258603018],"iteration":173,"passed_time":0.7021803213,"remaining_time":3.333338767},
{"learn":[0.4255940679],"iteration":174,"passed_time":0.7061365991,"remaining_time":3.328929682},
{"learn":[0.4253872914],"iteration":175,"passed_time":0.7101541235,"remaining_time":3.324812487},
{"learn":[0.4253091668],"iteration":176,"passed_time":0.7131697461,"remaining_time":3.316037859},
{"learn":[0.4250677644],"iteration":177,"passed_time":0.7171803958,"remaining_time":3.311922952},
{"learn":[0.4250534949],"iteration":178,"passed_time":0.7205533734,"remaining_time":3.304884467},
{"learn":[0.4249969447],"iteration":179,"passed_time":0.7245376086,"remaining_time":3.300671328},
{"learn":[0.4247928821],"iteration":180,"passed_time":0.7283111047,"remaining_time":3.295507153},
{"learn":[0.4247701069],"iteration":181,"passed_time":0.7318117001,"remaining_time":3.289131707},
{"learn":[0.4247497158],"iteration":182,"passed_time":0.7353937489,"remaining_time":3.283151327},
{"learn":[0.4245480592],"iteration":183,"passed_time":0.7390216701,"remaining_time":3.27740045},
{"learn":[0.4243619611],"iteration":184,"passed_time":0.7427465439,"remaining_time":3.272099639},
{"learn":[0.4243460765],"iteration":185,"passed_time":0.7464112551,"remaining_time":3.266552482},
{"learn":[0.4241621111],"iteration":186,"passed_time":0.7504872762,"remaining_time":3.262813666},
{"learn":[0.4239187639],"iteration":187,"passed_time":0.7540469092,"remaining_time":3.256840906},
{"learn":[0.4239039457],"iteration":188,"passed_time":0.7575690034,"remaining_time":3.250732602},
{"learn":[0.4236763848],"iteration":189,"passed_time":0.7612990439,"remaining_time":3.245538029},
{"learn":[0.4235057533],"iteration":190,"passed_time":0.7652877779,"remaining_time":3.241454515},
{"learn":[0.4233274803],"iteration":191,"passed_time":0.7693586743,"remaining_time":3.237717754},
{"learn":[0.4231582746],"iteration":192,"passed_time":0.7731600028,"remaining_time":3.232850374},
{"learn":[0.4229258823],"iteration":193,"passed_time":0.7765804777,"remaining_time":3.226411675},
{"learn":[0.4228852694],"iteration":194,"passed_time":0.7803205176,"remaining_time":3.221323162},
{"learn":[0.4228771799],"iteration":195,"passed_time":0.7833415149,"remaining_time":3.213298867},
{"learn":[0.4227875598],"iteration":196,"passed_time":0.7867872794,"remaining_time":3.207056778},
{"learn":[0.4226501972],"iteration":197,"passed_time":0.7906606448,"remaining_time":3.202574935},
{"learn":[0.4225767544],"iteration":198,"passed_time":0.7941982792,"remaining_time":3.196747847},
{"learn":[0.4225677411],"iteration":199,"passed_time":0.7980957273,"remaining_time":3.192382909},
{"learn":[0.422385672],"iteration":200,"passed_time":0.8017222736,"remaining_time":3.186945754},
{"learn":[0.4222195838],"iteration":201,"passed_time":0.8055504336,"remaining_time":3.182323},
{"learn":[0.4220753711],"iteration":202,"passed_time":0.8090555697,"remaining_time":3.176439848},
{"learn":[0.4219837932],"iteration":203,"passed_time":0.8123390523,"remaining_time":3.169715126},
{"learn":[0.4218252334],"iteration":204,"passed_time":0.8160958003,"remaining_time":3.164859323},
{"learn":[0.421644919],"iteration":205,"passed_time":0.8199224194,"remaining_time":3.1602835},
{"learn":[0.4215396383],"iteration":206,"passed_time":0.8233924325,"remaining_time":3.154348787},
{"learn":[0.4213314308],"iteration":207,"passed_time":0.8271675535,"remaining_time":3.14959953},
{"learn":[0.4213145953],"iteration":208,"passed_time":0.8306375256,"remaining_time":3.143704702},
{"learn":[0.4211299951],"iteration":209,"passed_time":0.8344666445,"remaining_time":3.139184044},
{"learn":[0.4208673185],"iteration":210,"passed_time":0.8381710204,"remaining_time":3.134203484},
{"learn":[0.4207264415],"iteration":211,"passed_time":0.8416708649,"remaining_time":3.128474724},
{"learn":[0.4207187343],"iteration":212,"passed_time":0.8451380031,"remaining_time":3.122646049},
{"learn":[0.4205318928],"iteration":213,"passed_time":0.8485793519,"remaining_time":3.116744722},
{"learn":[0.4204839444],"iteration":214,"passed_time":0.8520779894,"remaining_time":3.11107545},
{"learn":[0.4203670891],"iteration":215,"passed_time":0.8557687401,"remaining_time":3.106123575},
{"learn":[0.4201856452],"iteration":216,"passed_time":0.8597478086,"remaining_time":3.10222366},
{"learn":[0.4201734934],"iteration":217,"passed_time":0.8637669999,"remaining_time":3.098466944},
{"learn":[0.4200809877],"iteration":218,"passed_time":0.8674871239,"remaining_time":3.093641296},
{"learn":[0.4200737396],"iteration":219,"passed_time":0.8707920223,"remaining_time":3.087353534},
{"learn":[0.4199652632],"iteration":220,"passed_time":0.8742394537,"remaining_time":3.081595178},
{"learn":[0.4198612091],"iteration":221,"passed_time":0.8782971008,"remaining_time":3.077996146},
{"learn":[0.4197179071],"iteration":222,"passed_time":0.8818224438,"remaining_time":3.072538291},
{"learn":[0.4195778575],"iteration":223,"passed_time":0.8862310712,"remaining_time":3.070157639},
{"learn":[0.4194655515],"iteration":224,"passed_time":0.8899532781,"remaining_time":3.065394625},
{"learn":[0.4193504929],"iteration":225,"passed_time":0.8937676889,"remaining_time":3.060956598},
{"learn":[0.4192485136],"iteration":226,"passed_time":0.8969905909,"remaining_time":3.054509809},
{"learn":[0.4191032609],"iteration":227,"passed_time":0.9005523488,"remaining_time":3.049238655},
{"learn":[0.4190962889],"iteration":228,"passed_time":0.9038128737,"remaining_time":3.042968234},
{"learn":[0.418981447],"iteration":229,"passed_time":0.907261513,"remaining_time":3.037353761},
{"learn":[0.4189747194],"iteration":230,"passed_time":0.9107133601,"remaining_time":3.031768718},
{"learn":[0.4188281103],"iteration":231,"passed_time":0.9142862435,"remaining_time":3.026602737},
{"learn":[0.4187467594],"iteration":232,"passed_time":0.917482356,"remaining_time":3.020210159},
{"learn":[0.4186419954],"iteration":233,"passed_time":0.9211279432,"remaining_time":3.015316259},
{"learn":[0.4184040354],"iteration":234,"passed_time":0.9247784052,"remaining_time":3.010448851},
{"learn":[0.4182948576],"iteration":235,"passed_time":0.9281397994,"remaining_time":3.004655961},
{"learn":[0.4181962628],"iteration":236,"passed_time":0.931635895,"remaining_time":2.999317249},
{"learn":[0.4180640187],"iteration":237,"passed_time":0.935108408,"remaining_time":2.993918516},
{"learn":[0.4180552644],"iteration":238,"passed_time":0.9384578029,"remaining_time":2.988143883},
{"learn":[0.4178784113],"iteration":239,"passed_time":0.9422866708,"remaining_time":2.983907791},
{"learn":[0.417747361],"iteration":240,"passed_time":0.9459237576,"remaining_time":2.979071087},
{"learn":[0.4176325334],"iteration":241,"passed_time":0.9494649757,"remaining_time":2.973944015},
{"learn":[0.4175720187],"iteration":242,"passed_time":0.9527724989,"remaining_time":2.968101982},
{"learn":[0.4175656146],"iteration":243,"passed_time":0.9560427322,"remaining_time":2.962165187},
{"learn":[0.4174978401],"iteration":244,"passed_time":0.9602700368,"remaining_time":2.959199501},
{"learn":[0.4174312515],"iteration":245,"passed_time":0.9637086767,"remaining_time":2.953806269},
{"learn":[0.4173745447],"iteration":246,"passed_time":0.9671175692,"remaining_time":2.948338177},
{"learn":[0.4173026521],"iteration":247,"passed_time":0.9704994623,"remaining_time":2.942804821},
{"learn":[0.4171385026],"iteration":248,"passed_time":0.9743897028,"remaining_time":2.938821955},
{"learn":[0.417132599],"iteration":249,"passed_time":0.9777535139,"remaining_time":2.933260542},
{"learn":[0.4169888523],"iteration":250,"passed_time":0.9818051203,"remaining_time":2.929769064},
{"learn":[0.4169030173],"iteration":251,"passed_time":0.9851065599,"remaining_time":2.924046455},
{"learn":[0.4167340039],"iteration":252,"passed_time":0.9890629207,"remaining_time":2.920276687},
{"learn":[0.4166306162],"iteration":253,"passed_time":0.9929811586,"remaining_time":2.916393482},
{"learn":[0.4164231447],"iteration":254,"passed_time":0.9967036165,"remaining_time":2.911938017},
{"learn":[0.4162961307],"iteration":255,"passed_time":1.000571816,"remaining_time":2.907911841},
{"learn":[0.4161463827],"iteration":256,"passed_time":1.004426808,"remaining_time":2.903848709},
{"learn":[0.4161380551],"iteration":257,"passed_time":1.007517842,"remaining_time":2.897590073},
{"learn":[0.4160320431],"iteration":258,"passed_time":1.01151291,"remaining_time":2.89394234},
{"learn":[0.4160244297],"iteration":259,"passed_time":1.015521602,"remaining_time":2.890330712},
{"learn":[0.4159017292],"iteration":260,"passed_time":1.019260684,"remaining_time":2.885952664},
{"learn":[0.415873315],"iteration":261,"passed_time":1.022931102,"remaining_time":2.881386083},
{"learn":[0.4157755132],"iteration":262,"passed_time":1.026451488,"remaining_time":2.87640588},
{"learn":[0.415703419],"iteration":263,"passed_time":1.030210819,"remaining_time":2.872102888},
{"learn":[0.4154874754],"iteration":264,"passed_time":1.033998647,"remaining_time":2.867883039},
{"learn":[0.4154020044],"iteration":265,"passed_time":1.037646359,"remaining_time":2.863279803},
{"learn":[0.4153574851],"iteration":266,"passed_time":1.041296862,"remaining_time":2.858691385},
{"learn":[0.4153240935],"iteration":267,"passed_time":1.044728961,"remaining_time":2.853513431},
{"learn":[0.4153184587],"iteration":268,"passed_time":1.047585218,"remaining_time":2.846783622},
{"learn":[0.4152865836],"iteration":269,"passed_time":1.051271844,"remaining_time":2.842327577},
{"learn":[0.4152553312],"iteration":270,"passed_time":1.054812229,"remaining_time":2.837483819},
{"learn":[0.4152311063],"iteration":271,"passed_time":1.058446942,"remaining_time":2.832902109},
{"learn":[0.4150543003],"iteration":272,"passed_time":1.062053864,"remaining_time":2.828253331},
{"learn":[0.4149310209],"iteration":273,"passed_time":1.065658704,"remaining_time":2.823606638},
{"learn":[0.4147387382],"iteration":274,"passed_time":1.069646605,"remaining_time":2.819977412},
{"learn":[0.4146012655],"iteration":275,"passed_time":1.073389436,"remaining_time":2.815702725},
{"learn":[0.4145946393],"iteration":276,"passed_time":1.076857117,"remaining_time":2.810713702},
{"learn":[0.4145681225],"iteration":277,"passed_time":1.080149766,"remaining_time":2.805281046},
{"learn":[0.4144202178],"iteration":278,"passed_time":1.083104517,"remaining_time":2.798990526},
{"learn":[0.4142717644],"iteration":279,"passed_time":1.086823141,"remaining_time":2.794688077},
{"learn":[0.4142494717],"iteration":280,"passed_time":1.090508018,"remaining_time":2.790303434},
{"learn":[0.4141299106],"iteration":281,"passed_time":1.093434479,"remaining_time":2.783992751},
{"learn":[0.4141245898],"iteration":282,"passed_time":1.096120411,"remaining_time":2.777096589},
{"learn":[0.4140782399],"iteration":283,"passed_time":1.099687335,"remaining_time":2.77245117},
{"learn":[0.4140731124],"iteration":284,"passed_time":1.102900821,"remaining_time":2.766926621},
{"learn":[0.4138704006],"iteration":285,"passed_time":1.106826184,"remaining_time":2.763195437},
{"learn":[0.4136869516],"iteration":286,"passed_time":1.11049452,"remaining_time":2.758824364},
{"learn":[0.4135824568],"iteration":287,"passed_time":1.114027946,"remaining_time":2.754124644},
{"learn":[0.413459281],"iteration":288,"passed_time":1.117390424,"remaining_time":2.749012428},
{"learn":[0.4133650694],"iteration":289,"passed_time":1.121008305,"remaining_time":2.744537574},
{"learn":[0.4132969218],"iteration":290,"passed_time":1.124772302,"remaining_time":2.740424611},
{"learn":[0.4132107248],"iteration":291,"passed_time":1.128056075,"remaining_time":2.735149662},
{"learn":[0.4132057379],"iteration":292,"passed_time":1.131103862,"remaining_time":2.729318875},
{"learn":[0.4131340933],"iteration":293,"passed_time":1.134969645,"remaining_time":2.725471324},
{"learn":[0.4130705498],"iteration":294,"passed_time":1.138368995,"remaining_time":2.720508954},
{"learn":[0.4130304773],"iteration":295,"passed_time":1.14181226,"remaining_time":2.71566159},
{"learn":[0.4128652299],"iteration":296,"passed_time":1.145593088,"remaining_time":2.711622697},
{"learn":[0.4126229759],"iteration":297,"passed_time":1.149427789,"remaining_time":2.707712442},
{"learn":[0.4124817853],"iteration":298,"passed_time":1.153228658,"remaining_time":2.703723376},
{"learn":[0.4124099264],"iteration":299,"passed_time":1.15698049,"remaining_time":2.699621142},
{"learn":[0.4122819821],"iteration":300,"passed_time":1.16044167,"remaining_time":2.694846271},
{"learn":[0.4121778278],"iteration":301,"passed_time":1.164206667,"remaining_time":2.690782296},
{"learn":[0.4121709991],"iteration":302,"passed_time":1.167374405,"remaining_time":2.685346403},
{"learn":[0.4121456913],"iteration":303,"passed_time":1.170973703,"remaining_time":2.680913477},
{"learn":[0.4121409926],"iteration":304,"passed_time":1.174631081,"remaining_time":2.676618366},
{"learn":[0.41204568],"iteration":305,"passed_time":1.178039057,"remaining_time":2.671761783},
{"learn":[0.4118683986],"iteration":306,"passed_time":1.181727808,"remaining_time":2.667548439},
{"learn":[0.4117181622],"iteration":307,"passed_time":1.185293441,"remaining_time":2.663061888},
{"learn":[0.4116492551],"iteration":308,"passed_time":1.188953861,"remaining_time":2.658793262},
{"learn":[0.4116252435],"iteration":309,"passed_time":1.192689818,"remaining_time":2.654696692},
{"learn":[0.4115277873],"iteration":310,"passed_time":1.19656785,"remaining_time":2.650917199},
{"learn":[0.4114188589],"iteration":311,"passed_time":1.200178772,"remaining_time":2.646548062},
{"learn":[0.4112061208],"iteration":312,"passed_time":1.204136883,"remaining_time":2.642945811},
{"learn":[0.4111978737],"iteration":313,"passed_time":1.207337287,"remaining_time":2.637685921},
{"learn":[0.4111058594],"iteration":314,"passed_time":1.21116828,"remaining_time":2.633810387},
{"learn":[0.4109921815],"iteration":315,"passed_time":1.214645251,"remaining_time":2.629168834},
{"learn":[0.4108500757],"iteration":316,"passed_time":1.218405956,"remaining_time":2.625145955},
{"learn":[0.4108305981],"iteration":317,"passed_time":1.221769934,"remaining_time":2.620273883},
{"learn":[0.4107839974],"iteration":318,"passed_time":1.225021668,"remaining_time":2.615171649},
{"learn":[0.4107033713],"iteration":319,"passed_time":1.228668921,"remaining_time":2.610921458},
{"learn":[0.4105448218],"iteration":320,"passed_time":1.232585576,"remaining_time":2.607244879},
{"learn":[0.4104996374],"iteration":321,"passed_time":1.235894598,"remaining_time":2.602287384},
{"learn":[0.4103732457],"iteration":322,"passed_time":1.23972255,"remaining_time":2.598427761},
{"learn":[0.4102616293],"iteration":323,"passed_time":1.24333264,"remaining_time":2.594113779},
{"learn":[0.410153863],"iteration":324,"passed_time":1.246650036,"remaining_time":2.589196229},
{"learn":[0.410100934],"iteration":325,"passed_time":1.250398659,"remaining_time":2.585180049},
{"learn":[0.4100038158],"iteration":326,"passed_time":1.254049579,"remaining_time":2.580964424},
{"learn":[0.4099971288],"iteration":327,"passed_time":1.257478677,"remaining_time":2.576297778},
{"learn":[0.4099918285],"iteration":328,"passed_time":1.260721036,"remaining_time":2.571257797},
{"learn":[0.4098501815],"iteration":329,"passed_time":1.264574278,"remaining_time":2.567468988},
{"learn":[0.4098460029],"iteration":330,"passed_time":1.268368398,"remaining_time":2.563560296},
{"learn":[0.4098037644],"iteration":331,"passed_time":1.272478875,"remaining_time":2.56028882},
{"learn":[0.4097002939],"iteration":332,"passed_time":1.276304993,"remaining_time":2.556442733},
{"learn":[0.4096209292],"iteration":333,"passed_time":1.279683928,"remaining_time":2.551705078},
{"learn":[0.4095304839],"iteration":334,"passed_time":1.283119318,"remaining_time":2.547087602},
{"learn":[0.4094211673],"iteration":335,"passed_time":1.286891565,"remaining_time":2.543142855},
{"learn":[0.4092709464],"iteration":336,"passed_time":1.290999834,"remaining_time":2.539860209},
{"learn":[0.409147161],"iteration":337,"passed_time":1.294335605,"remaining_time":2.535059676},
{"learn":[0.4090764095],"iteration":338,"passed_time":1.298079145,"remaining_time":2.531062875},
{"learn":[0.4089810598],"iteration":339,"passed_time":1.301539618,"remaining_time":2.526518081},
{"learn":[0.4089768034],"iteration":340,"passed_time":1.30473798,"remaining_time":2.521473105},
{"learn":[0.4089726886],"iteration":341,"passed_time":1.30785318,"remaining_time":2.516278925},
{"learn":[0.4088742621],"iteration":342,"passed_time":1.311271238,"remaining_time":2.511676978},
{"learn":[0.408798784],"iteration":343,"passed_time":1.314858994,"remaining_time":2.507405524},
{"learn":[0.4087396383],"iteration":344,"passed_time":1.318104354,"remaining_time":2.502487977},
{"learn":[0.4086599344],"iteration":345,"passed_time":1.321677611,"remaining_time":2.498199878},
{"learn":[0.4085979102],"iteration":346,"passed_time":1.325084712,"remaining_time":2.493603219},
{"learn":[0.4085805654],"iteration":347,"passed_time":1.328361278,"remaining_time":2.488768831},
{"learn":[0.4084945088],"iteration":348,"passed_time":1.331979866,"remaining_time":2.484581354},
{"learn":[0.4083594934],"iteration":349,"passed_time":1.335617328,"remaining_time":2.48043218},
{"learn":[0.4082562978],"iteration":350,"passed_time":1.339588772,"remaining_time":2.476903455},
{"learn":[0.4082277097],"iteration":351,"passed_time":1.343100074,"remaining_time":2.472525137},
{"learn":[0.4081405347],"iteration":352,"passed_time":1.346883403,"remaining_time":2.468650316},
{"learn":[0.4081044977],"iteration":353,"passed_time":1.35014851,"remaining_time":2.463830333},
{"learn":[0.4080149509],"iteration":354,"passed_time":1.353755266,"remaining_time":2.459639849},
{"learn":[0.4079611023],"iteration":355,"passed_time":1.357037998,"remaining_time":2.454866492},
{"learn":[0.4078528262],"iteration":356,"passed_time":1.360505888,"remaining_time":2.450434974},
{"learn":[0.407744225],"iteration":357,"passed_time":1.364464999,"remaining_time":2.446889747},
{"learn":[0.4075637808],"iteration":358,"passed_time":1.368189832,"remaining_time":2.442923906},
{"learn":[0.4075021005],"iteration":359,"passed_time":1.371897333,"remaining_time":2.438928592},
{"learn":[0.407498099],"iteration":360,"passed_time":1.374897414,"remaining_time":2.433682681},
{"learn":[0.4073338247],"iteration":361,"passed_time":1.378479505,"remaining_time":2.429474929},
{"learn":[0.4072022573],"iteration":362,"passed_time":1.382399744,"remaining_time":2.425864014},
{"learn":[0.4071338064],"iteration":363,"passed_time":1.386312108,"remaining_time":2.42223764},
{"learn":[0.4070544142],"iteration":364,"passed_time":1.390308093,"remaining_time":2.418755175},
{"learn":[0.4069427505],"iteration":365,"passed_time":1.393903224,"remaining_time":2.41457553},
{"learn":[0.4069388958],"iteration":366,"passed_time":1.397703761,"remaining_time":2.410753353},
{"learn":[0.4068321881],"iteration":367,"passed_time":1.401043323,"remaining_time":2.40613962},
{"learn":[0.4067592338],"iteration":368,"passed_time":1.404963436,"remaining_time":2.40252555},
{"learn":[0.4066895077],"iteration":369,"passed_time":1.408638813,"remaining_time":2.398493115},
{"learn":[0.4066406272],"iteration":370,"passed_time":1.412485556,"remaining_time":2.39475314},
{"learn":[0.4065024266],"iteration":371,"passed_time":1.41603494,"remaining_time":2.390510598},
{"learn":[0.4064965041],"iteration":372,"passed_time":1.419510745,"remaining_time":2.386148088},
{"learn":[0.4064100969],"iteration":373,"passed_time":1.423042754,"remaining_time":2.381884396},
{"learn":[0.4063692665],"iteration":374,"passed_time":1.426760588,"remaining_time":2.377934313},
{"learn":[0.4062210268],"iteration":375,"passed_time":1.430573332,"remaining_time":2.374142977},
{"learn":[0.4061041921],"iteration":376,"passed_time":1.43400289,"remaining_time":2.369718303},
{"learn":[0.4059915386],"iteration":377,"passed_time":1.437450404,"remaining_time":2.365328443},
{"learn":[0.405897251],"iteration":378,"passed_time":1.441138572,"remaining_time":2.361337871},
{"learn":[0.405718593],"iteration":379,"passed_time":1.444647583,"remaining_time":2.357056583},
{"learn":[0.4056212027],"iteration":380,"passed_time":1.448291503,"remaining_time":2.352998532},
{"learn":[0.4056029822],"iteration":381,"passed_time":1.451863012,"remaining_time":2.348825501},
{"learn":[0.4055490044],"iteration":382,"passed_time":1.455117704,"remaining_time":2.344145231},
{"learn":[0.4055195703],"iteration":383,"passed_time":1.458736293,"remaining_time":2.340056136},
{"learn":[0.4054927874],"iteration":384,"passed_time":1.462568327,"remaining_time":2.336310445},
{"learn":[0.4053462735],"iteration":385,"passed_time":1.466944415,"remaining_time":2.333429717},
{"learn":[0.4052619922],"iteration":386,"passed_time":1.470715328,"remaining_time":2.329582677},
{"learn":[0.4051535734],"iteration":387,"passed_time":1.474151385,"remaining_time":2.325207854},
{"learn":[0.4050899445],"iteration":388,"passed_time":1.47785326,"remaining_time":2.321255377},
{"learn":[0.4050032415],"iteration":389,"passed_time":1.482126437,"remaining_time":2.31819776},
{"learn":[0.4049177737],"iteration":390,"passed_time":1.485572035,"remaining_time":2.313844935},
{"learn":[0.4048099059],"iteration":391,"passed_time":1.489346698,"remaining_time":2.310007124},
{"learn":[0.4047539307],"iteration":392,"passed_time":1.493022325,"remaining_time":2.30601667},
{"learn":[0.4046866594],"iteration":393,"passed_time":1.49645609,"remaining_time":2.301655814},
{"learn":[0.4045550236],"iteration":394,"passed_time":1.500156132,"remaining_time":2.297707494},
{"learn":[0.4044413689],"iteration":395,"passed_time":1.503614188,"remaining_time":2.293391337},
{"learn":[0.4043835038],"iteration":396,"passed_time":1.506970791,"remaining_time":2.288925407},
{"learn":[0.4043638488],"iteration":397,"passed_time":1.510669125,"remaining_time":2.284981943},
{"learn":[0.4042522522],"iteration":398,"passed_time":1.514573114,"remaining_time":2.281349477},
{"learn":[0.4042054294],"iteration":399,"passed_time":1.518032503,"remaining_time":2.277048755},
{"learn":[0.4040704971],"iteration":400,"passed_time":1.52170263,"remaining_time":2.273067021},
{"learn":[0.4039377764],"iteration":401,"passed_time":1.525301261,"remaining_time":2.268980483},
{"learn":[0.4039320485],"iteration":402,"passed_time":1.528759192,"remaining_time":2.264687934},
{"learn":[0.4039001675],"iteration":403,"passed_time":1.531875058,"remaining_time":2.259894887},
{"learn":[0.4038156427],"iteration":404,"passed_time":1.535730424,"remaining_time":2.256196549},
{"learn":[0.4038097202],"iteration":405,"passed_time":1.539179731,"remaining_time":2.25190335},
{"learn":[0.4037313638],"iteration":406,"passed_time":1.54266516,"remaining_time":2.247666928},
{"learn":[0.4036718828],"iteration":407,"passed_time":1.546332871,"remaining_time":2.243698675},
{"learn":[0.4036560317],"iteration":408,"passed_time":1.549809134,"remaining_time":2.239455252},
{"learn":[0.4035573997],"iteration":409,"passed_time":1.553477636,"remaining_time":2.235492207},
{"learn":[0.403537151],"iteration":410,"passed_time":1.556914443,"remaining_time":2.231198556},
{"learn":[0.4034011154],"iteration":411,"passed_time":1.560595278,"remaining_time":2.227257338},
{"learn":[0.4032773069],"iteration":412,"passed_time":1.564311736,"remaining_time":2.223368012},
{"learn":[0.4031266249],"iteration":413,"passed_time":1.568477877,"remaining_time":2.220116029},
{"learn":[0.4030443291],"iteration":414,"passed_time":1.571974097,"remaining_time":2.215915293},
{"learn":[0.4030390689],"iteration":415,"passed_time":1.575204999,"remaining_time":2.21134548},
{"learn":[0.4029378691],"iteration":416,"passed_time":1.579677206,"remaining_time":2.208517533},
{"learn":[0.4029342618],"iteration":417,"passed_time":1.583416371,"remaining_time":2.204661072},
{"learn":[0.4028948343],"iteration":418,"passed_time":1.587195159,"remaining_time":2.200860113},
{"learn":[0.402777799],"iteration":419,"passed_time":1.591202475,"remaining_time":2.197374846},
{"learn":[0.4027014292],"iteration":420,"passed_time":1.595207542,"remaining_time":2.193884006},
{"learn":[0.4026026605],"iteration":421,"passed_time":1.59871922,"remaining_time":2.18971495},
{"learn":[0.4025887276],"iteration":422,"passed_time":1.601866168,"remaining_time":2.185051487},
{"learn":[0.4025315847],"iteration":423,"passed_time":1.605656622,"remaining_time":2.181269373},
{"learn":[0.4023870888],"iteration":424,"passed_time":1.609548987,"remaining_time":2.1776251},
{"learn":[0.402263953],"iteration":425,"passed_time":1.613082455,"remaining_time":2.173496078},
{"learn":[0.4021925482],"iteration":426,"passed_time":1.617010109,"remaining_time":2.169898812},
{"learn":[0.4020704341],"iteration":427,"passed_time":1.620496204,"remaining_time":2.165709881},
{"learn":[0.402067359],"iteration":428,"passed_time":1.624016007,"remaining_time":2.161569091},
{"learn":[0.4019234997],"iteration":429,"passed_time":1.627469646,"remaining_time":2.157343484},
{"learn":[0.4018238329],"iteration":430,"passed_time":1.631234934,"remaining_time":2.153532895},
{"learn":[0.4018104081],"iteration":431,"passed_time":1.634664201,"remaining_time":2.149280708},
{"learn":[0.4017057083],"iteration":432,"passed_time":1.638120674,"remaining_time":2.145067949},
{"learn":[0.4016743063],"iteration":433,"passed_time":1.641271372,"remaining_time":2.140459899},
{"learn":[0.4016585686],"iteration":434,"passed_time":1.64468493,"remaining_time":2.136199966},
{"learn":[0.4015754595],"iteration":435,"passed_time":1.648219648,"remaining_time":2.132100646},
{"learn":[0.4015342337],"iteration":436,"passed_time":1.651734326,"remaining_time":2.12797809},
{"learn":[0.401422218],"iteration":437,"passed_time":1.655388496,"remaining_time":2.124037294},
{"learn":[0.4013649646],"iteration":438,"passed_time":1.659653256,"remaining_time":2.120878079},
{"learn":[0.4013525288],"iteration":439,"passed_time":1.66325572,"remaining_time":2.116870916},
{"learn":[0.4013040398],"iteration":440,"passed_time":1.667060756,"remaining_time":2.113122364},
{"learn":[0.4012064546],"iteration":441,"passed_time":1.670416901,"remaining_time":2.108806857},
{"learn":[0.4011610134],"iteration":442,"passed_time":1.67413365,"remaining_time":2.104949081},
{"learn":[0.4010914782],"iteration":443,"passed_time":1.677829359,"remaining_time":2.101065594},
{"learn":[0.4010216939],"iteration":444,"passed_time":1.681324247,"remaining_time":2.096932488},
{"learn":[0.4009228384],"iteration":445,"passed_time":1.685055829,"remaining_time":2.093096255},
{"learn":[0.4009067662],"iteration":446,"passed_time":1.688495844,"remaining_time":2.088899781},
{"learn":[0.4009015822],"iteration":447,"passed_time":1.691719663,"remaining_time":2.084440299},
{"learn":[0.4008452156],"iteration":448,"passed_time":1.695753895,"remaining_time":2.080980837},
{"learn":[0.400783081],"iteration":449,"passed_time":1.699498976,"remaining_time":2.077165415},
{"learn":[0.4006476578],"iteration":450,"passed_time":1.702866329,"remaining_time":2.072890498},
{"learn":[0.4006150863],"iteration":451,"passed_time":1.705985487,"remaining_time":2.068318688},
{"learn":[0.4006122671],"iteration":452,"passed_time":1.709391004,"remaining_time":2.064099071},
{"learn":[0.4005990407],"iteration":453,"passed_time":1.713265828,"remaining_time":2.06044745},
{"learn":[0.4005099145],"iteration":454,"passed_time":1.716944871,"remaining_time":2.056560341},
{"learn":[0.4004928516],"iteration":455,"passed_time":1.720303433,"remaining_time":2.052291815},
{"learn":[0.4004045773],"iteration":456,"passed_time":1.724303958,"remaining_time":2.048790042},
{"learn":[0.4003593523],"iteration":457,"passed_time":1.727714184,"remaining_time":2.044587527},
{"learn":[0.4003187672],"iteration":458,"passed_time":1.731065745,"remaining_time":2.040319321},
{"learn":[0.4002304698],"iteration":459,"passed_time":1.734491511,"remaining_time":2.036142209},
{"learn":[0.4001842855],"iteration":460,"passed_time":1.738142056,"remaining_time":2.032231167},
{"learn":[0.4001580197],"iteration":461,"passed_time":1.741581904,"remaining_time":2.028075897},
{"learn":[0.3999655318],"iteration":462,"passed_time":1.745307111,"remaining_time":2.024254684},
{"learn":[0.3999250231],"iteration":463,"passed_time":1.748777459,"remaining_time":2.020139478},
{"learn":[0.3999211209],"iteration":464,"passed_time":1.752241931,"remaining_time":2.016020286},
{"learn":[0.399870752],"iteration":465,"passed_time":1.755769441,"remaining_time":2.01197614},
{"learn":[0.3997897421],"iteration":466,"passed_time":1.759050632,"remaining_time":2.007653076},
{"learn":[0.3996935536],"iteration":467,"passed_time":1.762707842,"remaining_time":2.003761906},
{"learn":[0.3996532847],"iteration":468,"passed_time":1.766559001,"remaining_time":2.000091321},
{"learn":[0.3996424376],"iteration":469,"passed_time":1.770037723,"remaining_time":1.995999985},
{"learn":[0.3995773995],"iteration":470,"passed_time":1.773304122,"remaining_time":1.991672783},
{"learn":[0.3995120558],"iteration":471,"passed_time":1.777128116,"remaining_time":1.987973825},
{"learn":[0.39947492],"iteration":472,"passed_time":1.781752482,"remaining_time":1.985166084},
{"learn":[0.3993911533],"iteration":473,"passed_time":1.785637346,"remaining_time":1.981530051},
{"learn":[0.3993497088],"iteration":474,"passed_time":1.789450798,"remaining_time":1.97781404},
{"learn":[0.3992802498],"iteration":475,"passed_time":1.793224211,"remaining_time":1.974053543},
{"learn":[0.3992057774],"iteration":476,"passed_time":1.796880047,"remaining_time":1.970164077},
{"learn":[0.3991879923],"iteration":477,"passed_time":1.800334269,"remaining_time":1.966055415},
{"learn":[0.3991463461],"iteration":478,"passed_time":1.804154679,"remaining_time":1.962347783},
{"learn":[0.3990917821],"iteration":479,"passed_time":1.80783339,"remaining_time":1.958486172},
{"learn":[0.3989634448],"iteration":480,"passed_time":1.812000448,"remaining_time":1.95515225},
{"learn":[0.39894],"iteration":481,"passed_time":1.815218809,"remaining_time":1.950795317},
{"learn":[0.398877052],"iteration":482,"passed_time":1.818465586,"remaining_time":1.946473515},
{"learn":[0.3988645863],"iteration":483,"passed_time":1.821728902,"remaining_time":1.942173788},
{"learn":[0.3988353188],"iteration":484,"passed_time":1.824863059,"remaining_time":1.937741187},
{"learn":[0.3987948948],"iteration":485,"passed_time":1.828397528,"remaining_time":1.933737303},
{"learn":[0.3987003945],"iteration":486,"passed_time":1.831947661,"remaining_time":1.929751849},
{"learn":[0.3986741432],"iteration":487,"passed_time":1.835608873,"remaining_time":1.925884719},
{"learn":[0.3985998431],"iteration":488,"passed_time":1.839430866,"remaining_time":1.922186447},
{"learn":[0.3985381513],"iteration":489,"passed_time":1.843257526,"remaining_time":1.918492527},
{"learn":[0.3984435643],"iteration":490,"passed_time":1.84706327,"remaining_time":1.914776384},
{"learn":[0.3983485842],"iteration":491,"passed_time":1.850717606,"remaining_time":1.910903545},
{"learn":[0.3983446743],"iteration":492,"passed_time":1.8545221,"remaining_time":1.907186014},
{"learn":[0.3982497376],"iteration":493,"passed_time":1.85835851,"remaining_time":1.903500822},
{"learn":[0.3981834468],"iteration":494,"passed_time":1.862553608,"remaining_time":1.900180954},
{"learn":[0.3981697384],"iteration":495,"passed_time":1.866544718,"remaining_time":1.896650278},
{"learn":[0.3981284126],"iteration":496,"passed_time":1.870273467,"remaining_time":1.892852221},
{"learn":[0.3980846849],"iteration":497,"passed_time":1.873749105,"remaining_time":1.888799298},
{"learn":[0.3979894559],"iteration":498,"passed_time":1.877267866,"remaining_time":1.884791986},
{"learn":[0.3979670157],"iteration":499,"passed_time":1.880559181,"remaining_time":1.880559181},
{"learn":[0.3979507797],"iteration":500,"passed_time":1.884226391,"remaining_time":1.876704529},
{"learn":[0.3979130897],"iteration":501,"passed_time":1.88770028,"remaining_time":1.872658844},
{"learn":[0.3979083105],"iteration":502,"passed_time":1.89055787,"remaining_time":1.868006483},
{"learn":[0.397844473],"iteration":503,"passed_time":1.894210289,"remaining_time":1.864143459},
{"learn":[0.3978309415],"iteration":504,"passed_time":1.897344196,"remaining_time":1.859773024},
{"learn":[0.3978075252],"iteration":505,"passed_time":1.900691466,"remaining_time":1.855615779},
{"learn":[0.3977192095],"iteration":506,"passed_time":1.905059346,"remaining_time":1.852454157},
{"learn":[0.3976730667],"iteration":507,"passed_time":1.908511652,"remaining_time":1.848401049},
{"learn":[0.3975903537],"iteration":508,"passed_time":1.912410433,"remaining_time":1.844780988},
{"learn":[0.3975266801],"iteration":509,"passed_time":1.915557506,"remaining_time":1.840437604},
{"learn":[0.3974768684],"iteration":510,"passed_time":1.919080017,"remaining_time":1.836458176},
{"learn":[0.3973907073],"iteration":511,"passed_time":1.923606596,"remaining_time":1.833437537},
{"learn":[0.3973879521],"iteration":512,"passed_time":1.926926743,"remaining_time":1.829265738},
{"learn":[0.3973554692],"iteration":513,"passed_time":1.930253098,"remaining_time":1.825103124},
{"learn":[0.3972617709],"iteration":514,"passed_time":1.933800399,"remaining_time":1.821151832},
{"learn":[0.3972046547],"iteration":515,"passed_time":1.937703139,"remaining_time":1.817535502},
{"learn":[0.3971734018],"iteration":516,"passed_time":1.940994871,"remaining_time":1.813347239},
{"learn":[0.3970332889],"iteration":517,"passed_time":1.944891819,"remaining_time":1.809725592},
{"learn":[0.3969652551],"iteration":518,"passed_time":1.948234881,"remaining_time":1.805589553},
{"learn":[0.3969044258],"iteration":519,"passed_time":1.951833095,"remaining_time":1.801692088},
{"learn":[0.3968832082],"iteration":520,"passed_time":1.95508937,"remaining_time":1.797481398},
{"learn":[0.3968116724],"iteration":521,"passed_time":1.958685377,"remaining_time":1.79358546},
{"learn":[0.3968090149],"iteration":522,"passed_time":1.962339047,"remaining_time":1.789743261},
{"learn":[0.3967824084],"iteration":523,"passed_time":1.965498328,"remaining_time":1.785452679},
{"learn":[0.3967092947],"iteration":524,"passed_time":1.9694109,"remaining_time":1.781847957},
{"learn":[0.3966211741],"iteration":525,"passed_time":1.973802028,"remaining_time":1.778673311},
{"learn":[0.3966119928],"iteration":526,"passed_time":1.977235585,"remaining_time":1.774634596},
{"learn":[0.3965927221],"iteration":527,"passed_time":1.980814967,"remaining_time":1.770728531},
{"learn":[0.3964981803],"iteration":528,"passed_time":1.984299814,"remaining_time":1.766739532},
{"learn":[0.3963731304],"iteration":529,"passed_time":1.988644362,"remaining_time":1.763514811},
{"learn":[0.3963380867],"iteration":530,"passed_time":1.992246076,"remaining_time":1.759629774},
{"learn":[0.3962812043],"iteration":531,"passed_time":1.995925245,"remaining_time":1.755813937},
{"learn":[0.3962632709],"iteration":532,"passed_time":1.999196353,"remaining_time":1.751641082},
{"learn":[0.3962392674],"iteration":533,"passed_time":2.002431838,"remaining_time":1.747440518},
{"learn":[0.3961812708],"iteration":534,"passed_time":2.005864395,"remaining_time":1.743414848},
{"learn":[0.3961160157],"iteration":535,"passed_time":2.009071007,"remaining_time":1.739195797},
{"learn":[0.3961136962],"iteration":536,"passed_time":2.012770425,"remaining_time":1.735405413},
{"learn":[0.3960434249],"iteration":537,"passed_time":2.016498381,"remaining_time":1.731639874},
{"learn":[0.3960228507],"iteration":538,"passed_time":2.020165675,"remaining_time":1.72782259},
{"learn":[0.3958990722],"iteration":539,"passed_time":2.024013625,"remaining_time":1.724159755},
{"learn":[0.3958829362],"iteration":540,"passed_time":2.027448349,"remaining_time":1.720145642},
{"learn":[0.3958480149],"iteration":541,"passed_time":2.031156974,"remaining_time":1.716365118},
{"learn":[0.3958311214],"iteration":542,"passed_time":2.034690692,"remaining_time":1.712437655},
{"learn":[0.3958185202],"iteration":543,"passed_time":2.038412608,"remaining_time":1.708669392},
{"learn":[0.3957608188],"iteration":544,"passed_time":2.041804877,"remaining_time":1.70462609},
{"learn":[0.395584485],"iteration":545,"passed_time":2.045194644,"remaining_time":1.700583093},
{"learn":[0.3955148325],"iteration":546,"passed_time":2.04883519,"remaining_time":1.696750166},
{"learn":[0.3954680283],"iteration":547,"passed_time":2.053147948,"remaining_time":1.693472395},
{"learn":[0.3954173368],"iteration":548,"passed_time":2.056633919,"remaining_time":1.689511653},
{"learn":[0.3953543906],"iteration":549,"passed_time":2.060158013,"remaining_time":1.685583829},
{"learn":[0.3952769913],"iteration":550,"passed_time":2.063840556,"remaining_time":1.681786588},
{"learn":[0.3951870162],"iteration":551,"passed_time":2.067452561,"remaining_time":1.677932514},
{"learn":[0.3951829048],"iteration":552,"passed_time":2.070522347,"remaining_time":1.673641029},
{"learn":[0.3951434034],"iteration":553,"passed_time":2.074087814,"remaining_time":1.669753005},
{"learn":[0.3951028496],"iteration":554,"passed_time":2.077482248,"remaining_time":1.66572901},
{"learn":[0.3950389289],"iteration":555,"passed_time":2.080995968,"remaining_time":1.661802535},
{"learn":[0.3950268579],"iteration":556,"passed_time":2.084375903,"remaining_time":1.65777114},
{"learn":[0.3950028477],"iteration":557,"passed_time":2.088359762,"remaining_time":1.654220457},
{"learn":[0.3949791583],"iteration":558,"passed_time":2.091999766,"remaining_time":1.650396953},
{"learn":[0.3949010358],"iteration":559,"passed_time":2.09538241,"remaining_time":1.646371893},
{"learn":[0.3948001228],"iteration":560,"passed_time":2.099101118,"remaining_time":1.642612105},
{"learn":[0.3947976685],"iteration":561,"passed_time":2.102462179,"remaining_time":1.638573727},
{"learn":[0.3947359115],"iteration":562,"passed_time":2.106986341,"remaining_time":1.635440552},
{"learn":[0.3946573702],"iteration":563,"passed_time":2.110369026,"remaining_time":1.631420027},
{"learn":[0.3946069708],"iteration":564,"passed_time":2.11381829,"remaining_time":1.62745302},
{"learn":[0.394531133],"iteration":565,"passed_time":2.117536165,"remaining_time":1.623693809},
{"learn":[0.3943886706],"iteration":566,"passed_time":2.121195502,"remaining_time":1.619890039},
{"learn":[0.3943423445],"iteration":567,"passed_time":2.124903419,"remaining_time":1.616123727},
{"learn":[0.3942147887],"iteration":568,"passed_time":2.128375515,"remaining_time":1.612178993},
{"learn":[0.3941296568],"iteration":569,"passed_time":2.131778198,"remaining_time":1.608183553},
{"learn":[0.3941166733],"iteration":570,"passed_time":2.135118178,"remaining_time":1.604143079},
{"learn":[0.3940824234],"iteration":571,"passed_time":2.138348162,"remaining_time":1.600022751},
{"learn":[0.3940722803],"iteration":572,"passed_time":2.141735764,"remaining_time":1.596022987},
{"learn":[0.3940113345],"iteration":573,"passed_time":2.144775386,"remaining_time":1.591767098},
{"learn":[0.3939560055],"iteration":574,"passed_time":2.148657917,"remaining_time":1.588138461},
{"learn":[0.3939345796],"iteration":575,"passed_time":2.152088267,"remaining_time":1.584176085},
{"learn":[0.3938373557],"iteration":576,"passed_time":2.155701522,"remaining_time":1.580349643},
{"learn":[0.3938344781],"iteration":577,"passed_time":2.158660065,"remaining_time":1.57604593},
{"learn":[0.3938194561],"iteration":578,"passed_time":2.162072873,"remaining_time":1.572077167},
{"learn":[0.3937785435],"iteration":579,"passed_time":2.166006693,"remaining_time":1.568487605},
{"learn":[0.3937331868],"iteration":580,"passed_time":2.170037425,"remaining_time":1.564966749},
{"learn":[0.3936637816],"iteration":581,"passed_time":2.17412332,"remaining_time":1.561483759},
{"learn":[0.393527623],"iteration":582,"passed_time":2.178036017,"remaining_time":1.557874819},
{"learn":[0.3934580615],"iteration":583,"passed_time":2.181445617,"remaining_time":1.553906467},
{"learn":[0.3933840302],"iteration":584,"passed_time":2.185067497,"remaining_time":1.550090617},
{"learn":[0.3933666388],"iteration":585,"passed_time":2.188596048,"remaining_time":1.546209495},
{"learn":[0.3933050244],"iteration":586,"passed_time":2.192204263,"remaining_time":1.542385623},
{"learn":[0.3932886457],"iteration":587,"passed_time":2.195891181,"remaining_time":1.53861763},
{"learn":[0.3932462836],"iteration":588,"passed_time":2.199129832,"remaining_time":1.534537115},
{"learn":[0.393205957],"iteration":589,"passed_time":2.202984907,"remaining_time":1.530887817},
{"learn":[0.3931750183],"iteration":590,"passed_time":2.20632297,"remaining_time":1.526880025},
{"learn":[0.3930851048],"iteration":591,"passed_time":2.209802107,"remaining_time":1.522971723},
{"learn":[0.3930169111],"iteration":592,"passed_time":2.213397697,"remaining_time":1.519144794},
{"learn":[0.3930148552],"iteration":593,"passed_time":2.217092824,"remaining_time":1.515386678},
{"learn":[0.3929576889],"iteration":594,"passed_time":2.220903444,"remaining_time":1.511707386},
{"learn":[0.3929443626],"iteration":595,"passed_time":2.224333334,"remaining_time":1.507769576},
{"learn":[0.392934362],"iteration":596,"passed_time":2.227803639,"remaining_time":1.503860748},
{"learn":[0.3928904124],"iteration":597,"passed_time":2.231083288,"remaining_time":1.49982522},
{"learn":[0.3928711476],"iteration":598,"passed_time":2.234729916,"remaining_time":1.496037891},
{"learn":[0.3927885197],"iteration":599,"passed_time":2.238465915,"remaining_time":1.49231061},
{"learn":[0.3927229808],"iteration":600,"passed_time":2.241722817,"remaining_time":1.488265231},
{"learn":[0.3926286015],"iteration":601,"passed_time":2.245812587,"remaining_time":1.484773106},
{"learn":[0.3926192362],"iteration":602,"passed_time":2.250510531,"remaining_time":1.481679404},
{"learn":[0.3924892942],"iteration":603,"passed_time":2.254079165,"remaining_time":1.477839982},
{"learn":[0.3924697106],"iteration":604,"passed_time":2.258997888,"remaining_time":1.474882919},
{"learn":[0.3924388494],"iteration":605,"passed_time":2.262650558,"remaining_time":1.471096237},
{"learn":[0.3924263179],"iteration":606,"passed_time":2.269105446,"remaining_time":1.469124284},
{"learn":[0.3924071996],"iteration":607,"passed_time":2.272918273,"remaining_time":1.46543415},
{"learn":[0.3922334095],"iteration":608,"passed_time":2.277606885,"remaining_time":1.462305898},
{"learn":[0.392195771],"iteration":609,"passed_time":2.280809122,"remaining_time":1.458222226},
{"learn":[0.392115859],"iteration":610,"passed_time":2.285503651,"remaining_time":1.455091522},
{"learn":[0.3920944731],"iteration":611,"passed_time":2.289948401,"remaining_time":1.451797352},
{"learn":[0.3920279007],"iteration":612,"passed_time":2.294287199,"remaining_time":1.448432539},
{"learn":[0.3919107103],"iteration":613,"passed_time":2.318909441,"remaining_time":1.457816033},
{"learn":[0.3918125664],"iteration":614,"passed_time":2.323842705,"remaining_time":1.45476332},
{"learn":[0.3918013808],"iteration":615,"passed_time":2.330837812,"remaining_time":1.452989805},
{"learn":[0.3917877902],"iteration":616,"passed_time":2.33467143,"remaining_time":1.449236884},
{"learn":[0.3917754857],"iteration":617,"passed_time":2.338028033,"remaining_time":1.445188849},
{"learn":[0.3916793759],"iteration":618,"passed_time":2.341860859,"remaining_time":1.441436167},
{"learn":[0.3916470447],"iteration":619,"passed_time":2.3457221,"remaining_time":1.437700642},
{"learn":[0.3915433729],"iteration":620,"passed_time":2.34945989,"remaining_time":1.43388937},
{"learn":[0.3914498505],"iteration":621,"passed_time":2.353339756,"remaining_time":1.430164675},
{"learn":[0.3913279139],"iteration":622,"passed_time":2.357705844,"remaining_time":1.426733713},
{"learn":[0.3912825918],"iteration":623,"passed_time":2.361840695,"remaining_time":1.423160419},
{"learn":[0.3912047499],"iteration":624,"passed_time":2.36619845,"remaining_time":1.41971907},
{"learn":[0.3911232789],"iteration":625,"passed_time":2.369864119,"remaining_time":1.415861311},
{"learn":[0.3910197765],"iteration":626,"passed_time":2.372619382,"remaining_time":1.411462567},
{"learn":[0.3909632441],"iteration":627,"passed_time":2.376077313,"remaining_time":1.407485287},
{"learn":[0.3908493905],"iteration":628,"passed_time":2.380088712,"remaining_time":1.403836108},
{"learn":[0.390762872],"iteration":629,"passed_time":2.383858334,"remaining_time":1.400043783},
{"learn":[0.3907107386],"iteration":630,"passed_time":2.387445715,"remaining_time":1.396144959},
{"learn":[0.3906378514],"iteration":631,"passed_time":2.391436658,"remaining_time":1.392482105},
{"learn":[0.3905616368],"iteration":632,"passed_time":2.394797136,"remaining_time":1.388452684},
{"learn":[0.390492794],"iteration":633,"passed_time":2.398233902,"remaining_time":1.384469414},
{"learn":[0.3904741184],"iteration":634,"passed_time":2.401944569,"remaining_time":1.380645303},
{"learn":[0.3904248492],"iteration":635,"passed_time":2.405092892,"remaining_time":1.376499705},
{"learn":[0.3903386844],"iteration":636,"passed_time":2.408568905,"remaining_time":1.372543975},
{"learn":[0.3902636103],"iteration":637,"passed_time":2.412475893,"remaining_time":1.368834284},
{"learn":[0.3902231906],"iteration":638,"passed_time":2.416514333,"remaining_time":1.365198238},
{"learn":[0.3902212906],"iteration":639,"passed_time":2.419796191,"remaining_time":1.361135357},
{"learn":[0.3901754331],"iteration":640,"passed_time":2.423136587,"remaining_time":1.357107699},
{"learn":[0.390144613],"iteration":641,"passed_time":2.426815422,"remaining_time":1.353270905},
{"learn":[0.3900370864],"iteration":642,"passed_time":2.430507464,"remaining_time":1.349441936},
{"learn":[0.3899618039],"iteration":643,"passed_time":2.434178842,"remaining_time":1.345601969},
{"learn":[0.3898623022],"iteration":644,"passed_time":2.438057249,"remaining_time":1.341876471},
{"learn":[0.3898604364],"iteration":645,"passed_time":2.441313858,"remaining_time":1.337809761},
{"learn":[0.3898542592],"iteration":646,"passed_time":2.444684252,"remaining_time":1.333807637},
{"learn":[0.3898112523],"iteration":647,"passed_time":2.448276384,"remaining_time":1.329927912},
{"learn":[0.3897248924],"iteration":648,"passed_time":2.452641638,"remaining_time":1.326467203},
{"learn":[0.3896742606],"iteration":649,"passed_time":2.456218812,"remaining_time":1.322579361},
{"learn":[0.3895678893],"iteration":650,"passed_time":2.459665452,"remaining_time":1.318622493},
{"learn":[0.3894999086],"iteration":651,"passed_time":2.463504903,"remaining_time":1.31487685},
{"learn":[0.3894207762],"iteration":652,"passed_time":2.467436182,"remaining_time":1.311179717},
{"learn":[0.3893808348],"iteration":653,"passed_time":2.471251384,"remaining_time":1.307420457},
{"learn":[0.3893693942],"iteration":654,"passed_time":2.474901054,"remaining_time":1.303573838},
{"learn":[0.3893676043],"iteration":655,"passed_time":2.478380109,"remaining_time":1.29963835},
{"learn":[0.3893302068],"iteration":656,"passed_time":2.481864663,"remaining_time":1.295707122},
{"learn":[0.3892724664],"iteration":657,"passed_time":2.485135229,"remaining_time":1.291666031},
{"learn":[0.3892290852],"iteration":658,"passed_time":2.488284927,"remaining_time":1.287564735},
{"learn":[0.389149623],"iteration":659,"passed_time":2.491529704,"remaining_time":1.283515302},
{"learn":[0.389090073],"iteration":660,"passed_time":2.494829894,"remaining_time":1.279496723},
{"learn":[0.3890762752],"iteration":661,"passed_time":2.498479523,"remaining_time":1.275658729},
{"learn":[0.3890745333],"iteration":662,"passed_time":2.501590473,"remaining_time":1.271547495},
{"learn":[0.3890648597],"iteration":663,"passed_time":2.504633927,"remaining_time":1.26740512},
{"learn":[0.3890566345],"iteration":664,"passed_time":2.508230808,"remaining_time":1.263544843},
{"learn":[0.3889999458],"iteration":665,"passed_time":2.511549789,"remaining_time":1.25954599},
{"learn":[0.3889094182],"iteration":666,"passed_time":2.514769733,"remaining_time":1.255499732},
{"learn":[0.3888930374],"iteration":667,"passed_time":2.518313284,"remaining_time":1.251616782},
{"learn":[0.3888539249],"iteration":668,"passed_time":2.52189275,"remaining_time":1.247752616},
{"learn":[0.3888026249],"iteration":669,"passed_time":2.525852069,"remaining_time":1.244076392},
{"learn":[0.3887494428],"iteration":670,"passed_time":2.52958311,"remaining_time":1.240287397},
{"learn":[0.3887475368],"iteration":671,"passed_time":2.532576859,"remaining_time":1.236138705},
{"learn":[0.3887457058],"iteration":672,"passed_time":2.535508819,"remaining_time":1.231963423},
{"learn":[0.3887423816],"iteration":673,"passed_time":2.538789344,"remaining_time":1.227960424},
{"learn":[0.388666603],"iteration":674,"passed_time":2.542671668,"remaining_time":1.224249322},
{"learn":[0.3886580165],"iteration":675,"passed_time":2.546231218,"remaining_time":1.22038301},
{"learn":[0.3886113431],"iteration":676,"passed_time":2.549821808,"remaining_time":1.216532414},
{"learn":[0.3885043209],"iteration":677,"passed_time":2.553375692,"remaining_time":1.212665151},
{"learn":[0.3884546004],"iteration":678,"passed_time":2.556445727,"remaining_time":1.208570071},
{"learn":[0.3884528591],"iteration":679,"passed_time":2.559524554,"remaining_time":1.204482143},
{"learn":[0.3884265095],"iteration":680,"passed_time":2.563436335,"remaining_time":1.200787358},
{"learn":[0.3884106213],"iteration":681,"passed_time":2.567189541,"remaining_time":1.197017997},
{"learn":[0.3883306347],"iteration":682,"passed_time":2.570983703,"remaining_time":1.193267692},
{"learn":[0.3883087882],"iteration":683,"passed_time":2.574804613,"remaining_time":1.189529617},
{"learn":[0.3882560608],"iteration":684,"passed_time":2.578915424,"remaining_time":1.185924611},
{"learn":[0.3882493081],"iteration":685,"passed_time":2.582098829,"remaining_time":1.181893633},
{"learn":[0.3882249832],"iteration":686,"passed_time":2.585485014,"remaining_time":1.17795751},
{"learn":[0.3881336607],"iteration":687,"passed_time":2.589082604,"remaining_time":1.174118855},
{"learn":[0.3881285683],"iteration":688,"passed_time":2.5924115,"remaining_time":1.170159618},
{"learn":[0.3880328933],"iteration":689,"passed_time":2.595958843,"remaining_time":1.16630035},
{"learn":[0.3879899987],"iteration":690,"passed_time":2.599515351,"remaining_time":1.162446083},
{"learn":[0.3879566637],"iteration":691,"passed_time":2.603251807,"remaining_time":1.15867277},
{"learn":[0.3878680363],"iteration":692,"passed_time":2.606924809,"remaining_time":1.154871452},
{"learn":[0.3878002057],"iteration":693,"passed_time":2.610339283,"remaining_time":1.150956514},
{"learn":[0.3877739311],"iteration":694,"passed_time":2.613805797,"remaining_time":1.147065853},
{"learn":[0.3876627239],"iteration":695,"passed_time":2.617355722,"remaining_time":1.143212844},
{"learn":[0.3875822592],"iteration":696,"passed_time":2.620762115,"remaining_time":1.139298308},
{"learn":[0.3875580211],"iteration":697,"passed_time":2.62490134,"remaining_time":1.135702299},
{"learn":[0.3874630417],"iteration":698,"passed_time":2.628659463,"remaining_time":1.131940627},
{"learn":[0.3873854528],"iteration":699,"passed_time":2.632523579,"remaining_time":1.128224391},
{"learn":[0.387337045],"iteration":700,"passed_time":2.636082712,"remaining_time":1.124377648},
{"learn":[0.3873353573],"iteration":701,"passed_time":2.63917883,"remaining_time":1.120335173},
{"learn":[0.3873149889],"iteration":702,"passed_time":2.642988116,"remaining_time":1.116596686},
{"learn":[0.3873032],"iteration":703,"passed_time":2.647149591,"remaining_time":1.113006078},
{"learn":[0.3872891128],"iteration":704,"passed_time":2.650865257,"remaining_time":1.109227306},
{"learn":[0.3872514841],"iteration":705,"passed_time":2.654270899,"remaining_time":1.105319609},
{"learn":[0.3872498617],"iteration":706,"passed_time":2.657800159,"remaining_time":1.101464564},
{"learn":[0.3872375824],"iteration":707,"passed_time":2.661298712,"remaining_time":1.097597774},
{"learn":[0.3871851191],"iteration":708,"passed_time":2.665203784,"remaining_time":1.093898873},
{"learn":[0.3871434077],"iteration":709,"passed_time":2.668797415,"remaining_time":1.090072184},
{"learn":[0.387067273],"iteration":710,"passed_time":2.672827523,"remaining_time":1.086423564},
{"learn":[0.386982633],"iteration":711,"passed_time":2.676681723,"remaining_time":1.082702719},
{"learn":[0.386915681],"iteration":712,"passed_time":2.680194318,"remaining_time":1.078843996},
{"learn":[0.3869083959],"iteration":713,"passed_time":2.68420726,"remaining_time":1.075186661},
{"learn":[0.3869024218],"iteration":714,"passed_time":2.687694147,"remaining_time":1.071318646},
{"learn":[0.3868396145],"iteration":715,"passed_time":2.691287236,"remaining_time":1.06749382},
{"learn":[0.3868380576],"iteration":716,"passed_time":2.694606633,"remaining_time":1.063561614},
{"learn":[0.3868223163],"iteration":717,"passed_time":2.698426752,"remaining_time":1.059827777},
{"learn":[0.3868208168],"iteration":718,"passed_time":2.701843602,"remaining_time":1.055936095},
{"learn":[0.3867815412],"iteration":719,"passed_time":2.705437692,"remaining_time":1.052114658},
{"learn":[0.3866962581],"iteration":720,"passed_time":2.70893383,"remaining_time":1.048255948},
{"learn":[0.3866891826],"iteration":721,"passed_time":2.712409802,"remaining_time":1.044390478},
{"learn":[0.3866877378],"iteration":722,"passed_time":2.716192839,"remaining_time":1.040643729},
{"learn":[0.3866282383],"iteration":723,"passed_time":2.719555233,"remaining_time":1.036736525},
{"learn":[0.386563278],"iteration":724,"passed_time":2.72342935,"remaining_time":1.033024926},
{"learn":[0.3864991971],"iteration":725,"passed_time":2.727159556,"remaining_time":1.029258565},
{"learn":[0.3864319544],"iteration":726,"passed_time":2.730691025,"remaining_time":1.025417675},
{"learn":[0.3863601953],"iteration":727,"passed_time":2.734395942,"remaining_time":1.02164244},
{"learn":[0.386318236],"iteration":728,"passed_time":2.738101442,"remaining_time":1.017867614},
{"learn":[0.3862837073],"iteration":729,"passed_time":2.741285847,"remaining_time":1.013900245},
{"learn":[0.3862492119],"iteration":730,"passed_time":2.744906685,"remaining_time":1.01009562},
{"learn":[0.3862121871],"iteration":731,"passed_time":2.748425821,"remaining_time":1.006254262},
{"learn":[0.3862026259],"iteration":732,"passed_time":2.75166643,"remaining_time":1.002312328},
{"learn":[0.3860946795],"iteration":733,"passed_time":2.755331557,"remaining_time":0.99852615},
{"learn":[0.3860738425],"iteration":734,"passed_time":2.759000434,"remaining_time":0.994741653},
{"learn":[0.3860384752],"iteration":735,"passed_time":2.762683352,"remaining_time":0.9909625067},
{"learn":[0.3859898457],"iteration":736,"passed_time":2.766491721,"remaining_time":0.9872283889},
{"learn":[0.3859580668],"iteration":737,"passed_time":2.770641196,"remaining_time":0.9836151671},
{"learn":[0.3859433732],"iteration":738,"passed_time":2.774355112,"remaining_time":0.9798466635},
{"learn":[0.385906104],"iteration":739,"passed_time":2.777832209,"remaining_time":0.9759951005},
{"learn":[0.3858963635],"iteration":740,"passed_time":2.781544251,"remaining_time":0.9722266679},
{"learn":[0.385806929],"iteration":741,"passed_time":2.785339329,"remaining_time":0.9684872601},
{"learn":[0.3858003747],"iteration":742,"passed_time":2.788607688,"remaining_time":0.9645655125},
{"learn":[0.3857268597],"iteration":743,"passed_time":2.79227819,"remaining_time":0.9607838933},
{"learn":[0.3856926464],"iteration":744,"passed_time":2.795901486,"remaining_time":0.9569864148},
{"learn":[0.3856837481],"iteration":745,"passed_time":2.799384207,"remaining_time":0.9531415395},
{"learn":[0.3856374176],"iteration":746,"passed_time":2.8029138,"remaining_time":0.9493135094},
{"learn":[0.3856359956],"iteration":747,"passed_time":2.806583761,"remaining_time":0.9455335666},
{"learn":[0.3855907699],"iteration":748,"passed_time":2.810640616,"remaining_time":0.9418835711},
{"learn":[0.3855692984],"iteration":749,"passed_time":2.813800106,"remaining_time":0.9379333687},
{"learn":[0.3854782],"iteration":750,"passed_time":2.816957596,"remaining_time":0.9339846089},
{"learn":[0.3853905378],"iteration":751,"passed_time":2.82007513,"remaining_time":0.9300247768},
{"learn":[0.3853061036],"iteration":752,"passed_time":2.823289241,"remaining_time":0.9260988613},
{"learn":[0.3852498993],"iteration":753,"passed_time":2.826587889,"remaining_time":0.9222024146},
{"learn":[0.3851707124],"iteration":754,"passed_time":2.830012238,"remaining_time":0.9183483423},
{"learn":[0.385155367],"iteration":755,"passed_time":2.833339927,"remaining_time":0.9144642091},
{"learn":[0.3851261052],"iteration":756,"passed_time":2.836421253,"remaining_time":0.9105024631},
{"learn":[0.3850543447],"iteration":757,"passed_time":2.840019551,"remaining_time":0.906708089},
{"learn":[0.3849711817],"iteration":758,"passed_time":2.844141445,"remaining_time":0.9030804851},
{"learn":[0.384874061],"iteration":759,"passed_time":2.847655873,"remaining_time":0.8992597492},
{"learn":[0.3848172203],"iteration":760,"passed_time":2.850755782,"remaining_time":0.8953096347},
{"learn":[0.3847696372],"iteration":761,"passed_time":2.855199283,"remaining_time":0.8917814033},
{"learn":[0.384732477],"iteration":762,"passed_time":2.85832369,"remaining_time":0.8878410414},
{"learn":[0.3846724933],"iteration":763,"passed_time":2.861249901,"remaining_time":0.8838415925},
{"learn":[0.3846502223],"iteration":764,"passed_time":2.864056201,"remaining_time":0.8798081142},
{"learn":[0.3846488148],"iteration":765,"passed_time":2.866811963,"remaining_time":0.8757624011},
{"learn":[0.3845409117],"iteration":766,"passed_time":2.869782629,"remaining_time":0.8717853357},
{"learn":[0.3845105471],"iteration":767,"passed_time":2.873023655,"remaining_time":0.8678925624},
{"learn":[0.384490382],"iteration":768,"passed_time":2.876014737,"remaining_time":0.8639264034},
{"learn":[0.3844284051],"iteration":769,"passed_time":2.879064981,"remaining_time":0.859980449},
{"learn":[0.3843557144],"iteration":770,"passed_time":2.882230929,"remaining_time":0.8560711837},
{"learn":[0.3843045784],"iteration":771,"passed_time":2.885769855,"remaining_time":0.8522739986},
{"learn":[0.3842863973],"iteration":772,"passed_time":2.88870419,"remaining_time":0.8482999368},
{"learn":[0.3842341192],"iteration":773,"passed_time":2.891484159,"remaining_time":0.8442834883},
{"learn":[0.3841594179],"iteration":774,"passed_time":2.894658898,"remaining_time":0.8403848412},
{"learn":[0.3841514436],"iteration":775,"passed_time":2.89816291,"remaining_time":0.836583108},
{"learn":[0.3840748173],"iteration":776,"passed_time":2.901650214,"remaining_time":0.8327773458},
{"learn":[0.3840375356],"iteration":777,"passed_time":2.905008858,"remaining_time":0.8289356896},
{"learn":[0.3839847893],"iteration":778,"passed_time":2.908678319,"remaining_time":0.8251834513},
{"learn":[0.3839834064],"iteration":779,"passed_time":2.912313365,"remaining_time":0.8214217183},
{"learn":[0.3838485574],"iteration":780,"passed_time":2.915649845,"remaining_time":0.817576589},
{"learn":[0.3838177088],"iteration":781,"passed_time":2.919366928,"remaining_time":0.8138388622},
{"learn":[0.3837951365],"iteration":782,"passed_time":2.923004933,"remaining_time":0.8100792725},
{"learn":[0.3837900013],"iteration":783,"passed_time":2.926446114,"remaining_time":0.8062657662},
{"learn":[0.3837528186],"iteration":784,"passed_time":2.930062745,"remaining_time":0.8025012614},
{"learn":[0.3837235473],"iteration":785,"passed_time":2.933434265,"remaining_time":0.7986703978},
{"learn":[0.3836571354],"iteration":786,"passed_time":2.937494329,"remaining_time":0.7950270547},
{"learn":[0.3836060818],"iteration":787,"passed_time":2.941404943,"remaining_time":0.7913424466},
{"learn":[0.3835644524],"iteration":788,"passed_time":2.944868374,"remaining_time":0.7875376766},
{"learn":[0.3835287358],"iteration":789,"passed_time":2.948248143,"remaining_time":0.7837115316},
{"learn":[0.3835137052],"iteration":790,"passed_time":2.951810485,"remaining_time":0.7799347551},
{"learn":[0.383469078],"iteration":791,"passed_time":2.955565441,"remaining_time":0.7762091057},
{"learn":[0.3834580613],"iteration":792,"passed_time":2.959141657,"remaining_time":0.7724367251},
{"learn":[0.3834101047],"iteration":793,"passed_time":2.962814285,"remaining_time":0.7686898522},
{"learn":[0.3833687899],"iteration":794,"passed_time":2.966164013,"remaining_time":0.7648599026},
{"learn":[0.3833644509],"iteration":795,"passed_time":2.969386082,"remaining_time":0.760998443},
{"learn":[0.3833530501],"iteration":796,"passed_time":2.972858137,"remaining_time":0.7572022606},
{"learn":[0.3832885636],"iteration":797,"passed_time":2.976714461,"remaining_time":0.7535041618},
{"learn":[0.3831697221],"iteration":798,"passed_time":2.980145018,"remaining_time":0.749698559},
{"learn":[0.383096799],"iteration":799,"passed_time":2.984045382,"remaining_time":0.7460113456},
{"learn":[0.3830954699],"iteration":800,"passed_time":2.986985509,"remaining_time":0.7420850391},
{"learn":[0.3830044664],"iteration":801,"passed_time":2.990719216,"remaining_time":0.7383571133},
{"learn":[0.382965472],"iteration":802,"passed_time":2.994303224,"remaining_time":0.7345924473},
{"learn":[0.3828997552],"iteration":803,"passed_time":2.997865649,"remaining_time":0.7308229692},
{"learn":[0.3828586892],"iteration":804,"passed_time":3.001378368,"remaining_time":0.7270419649},
{"learn":[0.3827957112],"iteration":805,"passed_time":3.005034621,"remaining_time":0.7232961744},
{"learn":[0.3827332307],"iteration":806,"passed_time":3.008914819,"remaining_time":0.7196041638},
{"learn":[0.3827170078],"iteration":807,"passed_time":3.012604404,"remaining_time":0.7158663931},
{"learn":[0.3827003134],"iteration":808,"passed_time":3.01615108,"remaining_time":0.7120950016},
{"learn":[0.3826830221],"iteration":809,"passed_time":3.020067652,"remaining_time":0.7084109307},
{"learn":[0.3826239566],"iteration":810,"passed_time":3.024214294,"remaining_time":0.7047799033},
{"learn":[0.3825879402],"iteration":811,"passed_time":3.02774618,"remaining_time":0.7010052732},
{"learn":[0.3825518095],"iteration":812,"passed_time":3.031404432,"remaining_time":0.6972603061},
{"learn":[0.382545085],"iteration":813,"passed_time":3.035192345,"remaining_time":0.6935451795},
{"learn":[0.3825138881],"iteration":814,"passed_time":3.039696509,"remaining_time":0.689992459},
{"learn":[0.3824472767],"iteration":815,"passed_time":3.043405259,"remaining_time":0.6862580487},
{"learn":[0.3824459774],"iteration":816,"passed_time":3.046809401,"remaining_time":0.6824554717},
{"learn":[0.382364196],"iteration":817,"passed_time":3.050393784,"remaining_time":0.6786939715},
{"learn":[0.3823127941],"iteration":818,"passed_time":3.053798551,"remaining_time":0.6748932084},
{"learn":[0.3821650595],"iteration":819,"passed_time":3.05748851,"remaining_time":0.6711560145},
{"learn":[0.3821133233],"iteration":820,"passed_time":3.061490661,"remaining_time":0.6674870015},
{"learn":[0.3820598187],"iteration":821,"passed_time":3.064913593,"remaining_time":0.6636917513},
{"learn":[0.3820391993],"iteration":822,"passed_time":3.068560346,"remaining_time":0.6599455423},
{"learn":[0.3820214134],"iteration":823,"passed_time":3.072599328,"remaining_time":0.6562833515},
{"learn":[0.3819676751],"iteration":824,"passed_time":3.076006136,"remaining_time":0.6524861501},
{"learn":[0.3819339022],"iteration":825,"passed_time":3.079719761,"remaining_time":0.6487545259},
{"learn":[0.3818843201],"iteration":826,"passed_time":3.083514506,"remaining_time":0.6450399147},
{"learn":[0.3818634177],"iteration":827,"passed_time":3.087221714,"remaining_time":0.6413069262},
{"learn":[0.3818228224],"iteration":828,"passed_time":3.090870592,"remaining_time":0.6375619678},
{"learn":[0.3817871159],"iteration":829,"passed_time":3.094689753,"remaining_time":0.6338521181},
{"learn":[0.3816982133],"iteration":830,"passed_time":3.098227179,"remaining_time":0.6300847091},
{"learn":[0.3816646858],"iteration":831,"passed_time":3.101579699,"remaining_time":0.6262805161},
{"learn":[0.3816299935],"iteration":832,"passed_time":3.10550877,"remaining_time":0.6225929948},
{"learn":[0.3815843526],"iteration":833,"passed_time":3.10950988,"remaining_time":0.6189192326},
{"learn":[0.381506232],"iteration":834,"passed_time":3.11364398,"remaining_time":0.6152709662},
{"learn":[0.3814607594],"iteration":835,"passed_time":3.117159908,"remaining_time":0.611500269},
{"learn":[0.3814136727],"iteration":836,"passed_time":3.120980443,"remaining_time":0.6077895009},
{"learn":[0.3813050365],"iteration":837,"passed_time":3.125119711,"remaining_time":0.6041400873},
{"learn":[0.3813037366],"iteration":838,"passed_time":3.12849298,"remaining_time":0.6003425147},
{"learn":[0.3812852391],"iteration":839,"passed_time":3.131991826,"remaining_time":0.5965698716},
{"learn":[0.3811783597],"iteration":840,"passed_time":3.135511128,"remaining_time":0.5928017472},
{"learn":[0.381076309],"iteration":841,"passed_time":3.139226003,"remaining_time":0.5890709126},
{"learn":[0.3810227071],"iteration":842,"passed_time":3.142696933,"remaining_time":0.5852946838},
{"learn":[0.3809623001],"iteration":843,"passed_time":3.146279106,"remaining_time":0.5815397401},
{"learn":[0.380961047],"iteration":844,"passed_time":3.149357059,"remaining_time":0.5776927149},
{"learn":[0.3808921725],"iteration":845,"passed_time":3.152405221,"remaining_time":0.5738420852},
{"learn":[0.3808547655],"iteration":846,"passed_time":3.155891318,"remaining_time":0.5700724576},
{"learn":[0.3808124371],"iteration":847,"passed_time":3.159600026,"remaining_time":0.5663434009},
{"learn":[0.3808026021],"iteration":848,"passed_time":3.163040041,"remaining_time":0.5625666033},
{"learn":[0.3807583802],"iteration":849,"passed_time":3.166695128,"remaining_time":0.558828552},
{"learn":[0.380695809],"iteration":850,"passed_time":3.170416085,"remaining_time":0.5551022287},
{"learn":[0.3806471239],"iteration":851,"passed_time":3.173809228,"remaining_time":0.5513189739},
{"learn":[0.3805516797],"iteration":852,"passed_time":3.177486147,"remaining_time":0.5475855376},
{"learn":[0.3805413224],"iteration":853,"passed_time":3.180802168,"remaining_time":0.5437905347},
{"learn":[0.3805170881],"iteration":854,"passed_time":3.184221185,"remaining_time":0.5400141192},
{"learn":[0.3805055421],"iteration":855,"passed_time":3.187726447,"remaining_time":0.5362530471},
{"learn":[0.3804031039],"iteration":856,"passed_time":3.191438946,"remaining_time":0.532527152},
{"learn":[0.3803790543],"iteration":857,"passed_time":3.194747135,"remaining_time":0.5287343744},
{"learn":[0.3803385267],"iteration":858,"passed_time":3.198227399,"remaining_time":0.52497097},
{"learn":[0.3802715234],"iteration":859,"passed_time":3.202304879,"remaining_time":0.5213054454},
{"learn":[0.3802396039],"iteration":860,"passed_time":3.20673113,"remaining_time":0.5176952696},
{"learn":[0.380238369],"iteration":861,"passed_time":3.210525792,"remaining_time":0.5139820874},
{"learn":[0.3801905118],"iteration":862,"passed_time":3.214368576,"remaining_time":0.5102763557},
{"learn":[0.3801428582],"iteration":863,"passed_time":3.218204986,"remaining_time":0.5065693033},
{"learn":[0.3801333854],"iteration":864,"passed_time":3.221543965,"remaining_time":0.5027843183},
{"learn":[0.3800915073],"iteration":865,"passed_time":3.225443163,"remaining_time":0.4990870484},
{"learn":[0.3800751526],"iteration":866,"passed_time":3.228991756,"remaining_time":0.4953355289},
{"learn":[0.3800312488],"iteration":867,"passed_time":3.232643967,"remaining_time":0.4916002346},
{"learn":[0.3800005076],"iteration":868,"passed_time":3.236375382,"remaining_time":0.4878770714},
{"learn":[0.3799512581],"iteration":869,"passed_time":3.240281788,"remaining_time":0.4841800373},
{"learn":[0.3798860641],"iteration":870,"passed_time":3.244090408,"remaining_time":0.4804680397},
{"learn":[0.3798088826],"iteration":871,"passed_time":3.248105182,"remaining_time":0.4767860818},
{"learn":[0.3797474979],"iteration":872,"passed_time":3.251792559,"remaining_time":0.4730557331},
{"learn":[0.3796531529],"iteration":873,"passed_time":3.255621302,"remaining_time":0.4693458628},
{"learn":[0.379627476],"iteration":874,"passed_time":3.259084774,"remaining_time":0.4655835391},
{"learn":[0.3795955669],"iteration":875,"passed_time":3.263021803,"remaining_time":0.461888931},
{"learn":[0.3795645434],"iteration":876,"passed_time":3.266449985,"remaining_time":0.4581224038},
{"learn":[0.3794773358],"iteration":877,"passed_time":3.269544728,"remaining_time":0.4543103153},
{"learn":[0.3793424001],"iteration":878,"passed_time":3.27353217,"remaining_time":0.4506227447},
{"learn":[0.3792808163],"iteration":879,"passed_time":3.277292751,"remaining_time":0.446903557},
{"learn":[0.3792686397],"iteration":880,"passed_time":3.280556485,"remaining_time":0.4431171642},
{"learn":[0.3792530335],"iteration":881,"passed_time":3.283902214,"remaining_time":0.4393429266},
{"learn":[0.3792486394],"iteration":882,"passed_time":3.287247151,"remaining_time":0.4355695546},
{"learn":[0.3792393655],"iteration":883,"passed_time":3.290609296,"remaining_time":0.4317994099},
{"learn":[0.3791744887],"iteration":884,"passed_time":3.29430688,"remaining_time":0.4280737753},
{"learn":[0.3791342119],"iteration":885,"passed_time":3.297840931,"remaining_time":0.4243271627},
{"learn":[0.3790820671],"iteration":886,"passed_time":3.30137719,"remaining_time":0.4205813106},
{"learn":[0.3790292286],"iteration":887,"passed_time":3.305400673,"remaining_time":0.4168973822},
{"learn":[0.3789465175],"iteration":888,"passed_time":3.309311287,"remaining_time":0.4131985971},
{"learn":[0.3789050714],"iteration":889,"passed_time":3.312353366,"remaining_time":0.409391989},
{"learn":[0.3788773664],"iteration":890,"passed_time":3.316355057,"remaining_time":0.4057044907},
{"learn":[0.3788457059],"iteration":891,"passed_time":3.320148469,"remaining_time":0.4019910703},
{"learn":[0.3787626664],"iteration":892,"passed_time":3.324145578,"remaining_time":0.3983018777},
{"learn":[0.3786907417],"iteration":893,"passed_time":3.328295428,"remaining_time":0.3946301066},
{"learn":[0.3786339609],"iteration":894,"passed_time":3.33203326,"remaining_time":0.3909089299},
{"learn":[0.3786327537],"iteration":895,"passed_time":3.335142335,"remaining_time":0.3871147353},
{"learn":[0.3786077184],"iteration":896,"passed_time":3.338445566,"remaining_time":0.3833443627},
{"learn":[0.3786065132],"iteration":897,"passed_time":3.341601306,"remaining_time":0.3795582775},
{"learn":[0.3785198071],"iteration":898,"passed_time":3.345158064,"remaining_time":0.375818648},
{"learn":[0.3784238719],"iteration":899,"passed_time":3.348924186,"remaining_time":0.3721026873},
{"learn":[0.378418962],"iteration":900,"passed_time":3.352004305,"remaining_time":0.3683112388},
{"learn":[0.3783206406],"iteration":901,"passed_time":3.355801592,"remaining_time":0.364599286},
{"learn":[0.378295918],"iteration":902,"passed_time":3.359097949,"remaining_time":0.3608333345},
{"learn":[0.3782785078],"iteration":903,"passed_time":3.362572169,"remaining_time":0.35708731},
{"learn":[0.3781544358],"iteration":904,"passed_time":3.36664894,"remaining_time":0.3534051374},
{"learn":[0.3781193163],"iteration":905,"passed_time":3.370086163,"remaining_time":0.3496557388},
{"learn":[0.3780841927],"iteration":906,"passed_time":3.373880033,"remaining_time":0.3459435977},
{"learn":[0.3780794332],"iteration":907,"passed_time":3.377588075,"remaining_time":0.3422225803},
{"learn":[0.3780258154],"iteration":908,"passed_time":3.381380029,"remaining_time":0.3385099919},
{"learn":[0.378006985],"iteration":909,"passed_time":3.385030824,"remaining_time":0.3347832683},
{"learn":[0.3779598996],"iteration":910,"passed_time":3.389108345,"remaining_time":0.3310984003},
{"learn":[0.3779048196],"iteration":911,"passed_time":3.392554609,"remaining_time":0.3273517606},
{"learn":[0.377899194],"iteration":912,"passed_time":3.395777844,"remaining_time":0.3235845263},
{"learn":[0.3778574219],"iteration":913,"passed_time":3.399634087,"remaining_time":0.3198780432},
{"learn":[0.3778501224],"iteration":914,"passed_time":3.403523326,"remaining_time":0.3161742981},
{"learn":[0.3778057119],"iteration":915,"passed_time":3.407338612,"remaining_time":0.3124633662},
{"learn":[0.3777912608],"iteration":916,"passed_time":3.411267683,"remaining_time":0.3087625057},
{"learn":[0.3777765064],"iteration":917,"passed_time":3.414671075,"remaining_time":0.3050141919},
{"learn":[0.377712567],"iteration":918,"passed_time":3.418268707,"remaining_time":0.301283749},
{"learn":[0.377691047],"iteration":919,"passed_time":3.421599728,"remaining_time":0.2975304111},
{"learn":[0.3776694046],"iteration":920,"passed_time":3.425019369,"remaining_time":0.2937855919},
{"learn":[0.3776291269],"iteration":921,"passed_time":3.428672164,"remaining_time":0.2900612026},
{"learn":[0.3776096835],"iteration":922,"passed_time":3.432429911,"remaining_time":0.2863457239},
{"learn":[0.377604329],"iteration":923,"passed_time":3.435953671,"remaining_time":0.282610908},
{"learn":[0.3776031798],"iteration":924,"passed_time":3.439629465,"remaining_time":0.2788888755},
{"learn":[0.3774924924],"iteration":925,"passed_time":3.443476789,"remaining_time":0.2751806506},
{"learn":[0.3774721295],"iteration":926,"passed_time":3.446734815,"remaining_time":0.271425719},
{"learn":[0.3774335057],"iteration":927,"passed_time":3.450494063,"remaining_time":0.2677107463},
{"learn":[0.3774187266],"iteration":928,"passed_time":3.454221354,"remaining_time":0.2639932359},
{"learn":[0.3774087296],"iteration":929,"passed_time":3.457587082,"remaining_time":0.26024849},
{"learn":[0.3774075842],"iteration":930,"passed_time":3.46097535,"remaining_time":0.2565062289},
{"learn":[0.3773993466],"iteration":931,"passed_time":3.464603855,"remaining_time":0.2527822555},
{"learn":[0.3773475918],"iteration":932,"passed_time":3.468504594,"remaining_time":0.2490780362},
{"learn":[0.3772411477],"iteration":933,"passed_time":3.472135723,"remaining_time":0.2453543444},
{"learn":[0.3771905284],"iteration":934,"passed_time":3.475972715,"remaining_time":0.241645162},
{"learn":[0.3771357819],"iteration":935,"passed_time":3.479632385,"remaining_time":0.2379235819},
{"learn":[0.3770982465],"iteration":936,"passed_time":3.483322678,"remaining_time":0.2342041928},
{"learn":[0.3770843905],"iteration":937,"passed_time":3.486822898,"remaining_time":0.2304723024},
{"learn":[0.3770483027],"iteration":938,"passed_time":3.490180876,"remaining_time":0.226731665},
{"learn":[0.3769983537],"iteration":939,"passed_time":3.49380434,"remaining_time":0.2230087876},
{"learn":[0.3769482084],"iteration":940,"passed_time":3.497434636,"remaining_time":0.21928655},
{"learn":[0.37694698],"iteration":941,"passed_time":3.500777448,"remaining_time":0.2155468068},
{"learn":[0.3768810041],"iteration":942,"passed_time":3.504477907,"remaining_time":0.2118295236},
{"learn":[0.3768659926],"iteration":943,"passed_time":3.507969211,"remaining_time":0.2080998685},
{"learn":[0.3768291912],"iteration":944,"passed_time":3.511762289,"remaining_time":0.2043882814},
{"learn":[0.3767996183],"iteration":945,"passed_time":3.515810604,"remaining_time":0.2006910916},
{"learn":[0.3767470113],"iteration":946,"passed_time":3.519860959,"remaining_time":0.1969932744},
{"learn":[0.3767397922],"iteration":947,"passed_time":3.523358388,"remaining_time":0.1932643841},
{"learn":[0.3767387277],"iteration":948,"passed_time":3.526497795,"remaining_time":0.1895167413},
{"learn":[0.3767209865],"iteration":949,"passed_time":3.529417631,"remaining_time":0.1857588227},
{"learn":[0.3766678921],"iteration":950,"passed_time":3.533656393,"remaining_time":0.1820706238},
{"learn":[0.376616825],"iteration":951,"passed_time":3.537162071,"remaining_time":0.1783443061},
{"learn":[0.3766033891],"iteration":952,"passed_time":3.540403722,"remaining_time":0.1746054301},
{"learn":[0.3765516099],"iteration":953,"passed_time":3.544052559,"remaining_time":0.1708872303},
{"learn":[0.376533157],"iteration":954,"passed_time":3.547630358,"remaining_time":0.1671658284},
{"learn":[0.3764908721],"iteration":955,"passed_time":3.551195074,"remaining_time":0.1634441248},
{"learn":[0.3764897142],"iteration":956,"passed_time":3.554517221,"remaining_time":0.1597118501},
{"learn":[0.376488698],"iteration":957,"passed_time":3.557740415,"remaining_time":0.1559760933},
{"learn":[0.3764778991],"iteration":958,"passed_time":3.561301465,"remaining_time":0.1522558499},
{"learn":[0.3764250059],"iteration":959,"passed_time":3.564866057,"remaining_time":0.1485360857},
{"learn":[0.3764071868],"iteration":960,"passed_time":3.568608721,"remaining_time":0.1448238711},
{"learn":[0.3763737763],"iteration":961,"passed_time":3.572333471,"remaining_time":0.1411108856},
{"learn":[0.3763429678],"iteration":962,"passed_time":3.576260251,"remaining_time":0.1374056379},
{"learn":[0.3763348254],"iteration":963,"passed_time":3.579429031,"remaining_time":0.1336716236},
{"learn":[0.3763172822],"iteration":964,"passed_time":3.582842422,"remaining_time":0.1299476526},
{"learn":[0.3762704025],"iteration":965,"passed_time":3.58647176,"remaining_time":0.1262319253},
{"learn":[0.3762334912],"iteration":966,"passed_time":3.590072016,"remaining_time":0.1225153842},
{"learn":[0.3762188905],"iteration":967,"passed_time":3.59311647,"remaining_time":0.1187807098},
{"learn":[0.3761878402],"iteration":968,"passed_time":3.596826387,"remaining_time":0.1150687492},
{"learn":[0.3761789957],"iteration":969,"passed_time":3.600337689,"remaining_time":0.1113506502},
{"learn":[0.3761138191],"iteration":970,"passed_time":3.604346505,"remaining_time":0.1076478359},
{"learn":[0.3760880211],"iteration":971,"passed_time":3.607904846,"remaining_time":0.1039314153},
{"learn":[0.3759812262],"iteration":972,"passed_time":3.612162607,"remaining_time":0.1002347281},
{"learn":[0.3759227158],"iteration":973,"passed_time":3.615809611,"remaining_time":0.09652058511},
{"learn":[0.3759037336],"iteration":974,"passed_time":3.619325289,"remaining_time":0.09280321254},
{"learn":[0.3758982797],"iteration":975,"passed_time":3.622704849,"remaining_time":0.08908290613},
{"learn":[0.3758399676],"iteration":976,"passed_time":3.626607505,"remaining_time":0.08537561168},
{"learn":[0.3757818584],"iteration":977,"passed_time":3.630742482,"remaining_time":0.08167314376},
{"learn":[0.3756977506],"iteration":978,"passed_time":3.634290033,"remaining_time":0.07795719171},
{"learn":[0.3756404909],"iteration":979,"passed_time":3.637953286,"remaining_time":0.07424394461},
{"learn":[0.3755879618],"iteration":980,"passed_time":3.641745407,"remaining_time":0.07053329534},
{"learn":[0.3755501498],"iteration":981,"passed_time":3.645295957,"remaining_time":0.06681805217},
{"learn":[0.375549096],"iteration":982,"passed_time":3.648246375,"remaining_time":0.06309276538},
{"learn":[0.3755480945],"iteration":983,"passed_time":3.65162881,"remaining_time":0.05937607821},
{"learn":[0.3755219816],"iteration":984,"passed_time":3.655318519,"remaining_time":0.05566474903},
{"learn":[0.3754684129],"iteration":985,"passed_time":3.659153346,"remaining_time":0.05195552418},
{"learn":[0.3754593782],"iteration":986,"passed_time":3.662583195,"remaining_time":0.04824071078},
{"learn":[0.3754107833],"iteration":987,"passed_time":3.666436854,"remaining_time":0.04453162171},
{"learn":[0.3753426222],"iteration":988,"passed_time":3.670254724,"remaining_time":0.04082184222},
{"learn":[0.3753020734],"iteration":989,"passed_time":3.673851855,"remaining_time":0.03710961469},
{"learn":[0.3752849371],"iteration":990,"passed_time":3.677000012,"remaining_time":0.03339354198},
{"learn":[0.3752283512],"iteration":991,"passed_time":3.680363365,"remaining_time":0.02968034972},
{"learn":[0.3751784775],"iteration":992,"passed_time":3.684053992,"remaining_time":0.02597016912},
{"learn":[0.3751026168],"iteration":993,"passed_time":3.687765741,"remaining_time":0.02226015538},
{"learn":[0.3750940882],"iteration":994,"passed_time":3.691047473,"remaining_time":0.01854797725},
{"learn":[0.3750646767],"iteration":995,"passed_time":3.694577233,"remaining_time":0.01483765957},
{"learn":[0.3749773853],"iteration":996,"passed_time":3.698631964,"remaining_time":0.01112928374},
{"learn":[0.3749485574],"iteration":997,"passed_time":3.702189223,"remaining_time":0.00741921688},
{"learn":[0.3749224337],"iteration":998,"passed_time":3.705434625,"remaining_time":0.003709143768},
{"learn":[0.3748852042],"iteration":999,"passed_time":3.709324114,"remaining_time":0}
]}